[
  {
    "name": "BTorrent",
    "full_name": "DiegoRBaquero/BTorrent",
    "html_url": "https://github.com/DiegoRBaquero/BTorrent",
    "description": ":globe_with_meridians: Fully-featured WebTorrent Client",
    "stars": 575,
    "forks": 96,
    "languages": {
      "HTML": 11005,
      "JavaScript": 10868,
      "CSS": 1574
    },
    "contributions_by_user": 158,
    "contribution_score": 3125.45,
    "S_code": 22.9,
    "S_social": 767,
    "S_maint": 158
  },
  {
    "name": "node-fb-messenger",
    "full_name": "DiegoRBaquero/node-fb-messenger",
    "html_url": "https://github.com/DiegoRBaquero/node-fb-messenger",
    "description": ":envelope: Facebook Messenger Platform Node.js API Wrapper",
    "stars": 210,
    "forks": 47,
    "languages": {
      "JavaScript": 6690
    },
    "contributions_by_user": 47,
    "contribution_score": 1081.27,
    "S_code": 6.53,
    "S_social": 304,
    "S_maint": 47
  },
  {
    "name": "awesome-webtorrent-clones",
    "full_name": "DiegoRBaquero/awesome-webtorrent-clones",
    "html_url": "https://github.com/DiegoRBaquero/awesome-webtorrent-clones",
    "description": "👥 Product clones using WebTorrent/WebRTC",
    "stars": 200,
    "forks": 13,
    "languages": {},
    "contributions_by_user": 18,
    "contribution_score": 632.0,
    "S_code": 0.0,
    "S_social": 226,
    "S_maint": 18
  },
  {
    "name": "PeerFast",
    "full_name": "DiegoRBaquero/PeerFast",
    "html_url": "https://github.com/DiegoRBaquero/PeerFast",
    "description": "⚡️ P2P Fast.com Clone",
    "stars": 105,
    "forks": 12,
    "languages": {
      "HTML": 4507
    },
    "contributions_by_user": 20,
    "contribution_score": 460.2,
    "S_code": 4.4,
    "S_social": 129,
    "S_maint": 20
  },
  {
    "name": "uWebTorrentTracker",
    "full_name": "DiegoRBaquero/uWebTorrentTracker",
    "html_url": "https://github.com/DiegoRBaquero/uWebTorrentTracker",
    "description": "🔆 Simple, robust, WebTorrent tracker server implementation",
    "stars": 63,
    "forks": 9,
    "languages": {
      "JavaScript": 52185
    },
    "contributions_by_user": 109,
    "contribution_score": 1277.48,
    "S_code": 50.96,
    "S_social": 81,
    "S_maint": 109
  },
  {
    "name": "node-v",
    "full_name": "DiegoRBaquero/node-v",
    "html_url": "https://github.com/DiegoRBaquero/node-v",
    "description": "🔒 Secure ❄️ Synchronized ⚡️ Realtime ☁️ Cloud 🌈 Native JavaScript Variables & Events",
    "stars": 28,
    "forks": 4,
    "languages": {
      "JavaScript": 191896
    },
    "contributions_by_user": 151,
    "contribution_score": 1675.7,
    "S_code": 187.4,
    "S_social": 36,
    "S_maint": 151
  },
  {
    "name": "node-os",
    "full_name": "DiegoRBaquero/node-os",
    "html_url": "https://github.com/DiegoRBaquero/node-os",
    "description": "NodeJS Core Module",
    "stars": 20,
    "forks": 6,
    "languages": {
      "JavaScript": 31
    },
    "contributions_by_user": 6,
    "contribution_score": 124.02,
    "S_code": 0.03,
    "S_social": 32,
    "S_maint": 6
  },
  {
    "name": "PeerTube",
    "full_name": "DiegoRBaquero/PeerTube",
    "html_url": "https://github.com/DiegoRBaquero/PeerTube",
    "description": "YouTube Clone using WebTorrent",
    "stars": 18,
    "forks": 6,
    "languages": {
      "JavaScript": 574596,
      "HTML": 4824,
      "CSS": 31
    },
    "contributions_by_user": 18,
    "contribution_score": 522.94,
    "S_code": 565.87,
    "S_social": 30,
    "S_maint": 18
  },
  {
    "name": "node-bogota",
    "full_name": "DiegoRBaquero/node-bogota",
    "html_url": "https://github.com/DiegoRBaquero/node-bogota",
    "description": "🚀 Run tape tests concurrently with tap-spec output",
    "stars": 15,
    "forks": 0,
    "languages": {
      "JavaScript": 5988
    },
    "contributions_by_user": 68,
    "contribution_score": 712.92,
    "S_code": 5.85,
    "S_social": 15,
    "S_maint": 68
  },
  {
    "name": "node-1337",
    "full_name": "DiegoRBaquero/node-1337",
    "html_url": "https://github.com/DiegoRBaquero/node-1337",
    "description": "Node leet speak conversion",
    "stars": 13,
    "forks": 0,
    "languages": {
      "JavaScript": 1423
    },
    "contributions_by_user": 25,
    "contribution_score": 276.69,
    "S_code": 1.39,
    "S_social": 13,
    "S_maint": 25
  },
  {
    "name": "node-vm",
    "full_name": "DiegoRBaquero/node-vm",
    "html_url": "https://github.com/DiegoRBaquero/node-vm",
    "description": "NodeJS Core Module",
    "stars": 11,
    "forks": 1,
    "languages": {
      "JavaScript": 31
    },
    "contributions_by_user": 4,
    "contribution_score": 66.02,
    "S_code": 0.03,
    "S_social": 13,
    "S_maint": 4
  },
  {
    "name": "uniandes-auto-wifi",
    "full_name": "DiegoRBaquero/uniandes-auto-wifi",
    "html_url": "https://github.com/DiegoRBaquero/uniandes-auto-wifi",
    "description": "Aplicación para conectarse automáticamente a SENECA",
    "stars": 9,
    "forks": 1,
    "languages": {
      "JavaScript": 8468,
      "HTML": 1834,
      "CSS": 255
    },
    "contributions_by_user": 15,
    "contribution_score": 177.15,
    "S_code": 10.31,
    "S_social": 11,
    "S_maint": 15
  },
  {
    "name": "apk-decompiler",
    "full_name": "DiegoRBaquero/apk-decompiler",
    "html_url": "https://github.com/DiegoRBaquero/apk-decompiler",
    "description": "Decompiles APK to dex, smali and java files",
    "stars": 6,
    "forks": 4,
    "languages": {
      "Shell": 11227,
      "Batchfile": 7853
    },
    "contributions_by_user": 2,
    "contribution_score": 57.32,
    "S_code": 18.63,
    "S_social": 14,
    "S_maint": 2
  },
  {
    "name": "ls-chunk-store",
    "full_name": "DiegoRBaquero/ls-chunk-store",
    "html_url": "https://github.com/DiegoRBaquero/ls-chunk-store",
    "description": "Browser localStorage chunk store that is abstract-chunk-store compliant",
    "stars": 5,
    "forks": 0,
    "languages": {
      "JavaScript": 3819
    },
    "contributions_by_user": 39,
    "contribution_score": 401.86,
    "S_code": 3.73,
    "S_social": 5,
    "S_maint": 39
  },
  {
    "name": "node-sr",
    "full_name": "DiegoRBaquero/node-sr",
    "html_url": "https://github.com/DiegoRBaquero/node-sr",
    "description": "Unblock your event loop! Require modules in a child process effortlessly",
    "stars": 4,
    "forks": 0,
    "languages": {
      "JavaScript": 5622
    },
    "contributions_by_user": 21,
    "contribution_score": 220.75,
    "S_code": 5.49,
    "S_social": 4,
    "S_maint": 21
  },
  {
    "name": "geostatistics-project",
    "full_name": "DiegoRBaquero/geostatistics-project",
    "html_url": "https://github.com/DiegoRBaquero/geostatistics-project",
    "description": "Geostatistics Project using Goverment's Open Data Personal Robberies in Bogotá 2017",
    "stars": 4,
    "forks": 0,
    "languages": {
      "HTML": 11361
    },
    "contributions_by_user": 9,
    "contribution_score": 103.55,
    "S_code": 11.09,
    "S_social": 4,
    "S_maint": 9
  },
  {
    "name": "BMagnet",
    "full_name": "DiegoRBaquero/BMagnet",
    "html_url": "https://github.com/DiegoRBaquero/BMagnet",
    "description": "An extension to the magnet URI scheme for WebTorrent",
    "stars": 3,
    "forks": 0,
    "languages": {
      "JavaScript": 588
    },
    "contributions_by_user": 10,
    "contribution_score": 106.29,
    "S_code": 0.57,
    "S_social": 3,
    "S_maint": 10
  },
  {
    "name": "awesome-open-source-organizations",
    "full_name": "DiegoRBaquero/awesome-open-source-organizations",
    "html_url": "https://github.com/DiegoRBaquero/awesome-open-source-organizations",
    "description": "A list of organizations that have open sourced everything they do",
    "stars": 3,
    "forks": 0,
    "languages": {},
    "contributions_by_user": 0,
    "contribution_score": 6.0,
    "S_code": 0.0,
    "S_social": 3,
    "S_maint": 0
  },
  {
    "name": "express-route-autoloader",
    "full_name": "DiegoRBaquero/express-route-autoloader",
    "html_url": "https://github.com/DiegoRBaquero/express-route-autoloader",
    "description": "Automatically loads routes from a directory structure",
    "stars": 2,
    "forks": 0,
    "languages": {
      "JavaScript": 1797
    },
    "contributions_by_user": 47,
    "contribution_score": 474.88,
    "S_code": 1.75,
    "S_social": 2,
    "S_maint": 47
  },
  {
    "name": "lf-chunk-store",
    "full_name": "DiegoRBaquero/lf-chunk-store",
    "html_url": "https://github.com/DiegoRBaquero/lf-chunk-store",
    "description": "Browser localForage chunk store that is abstract-chunk-store compliant",
    "stars": 2,
    "forks": 1,
    "languages": {
      "JavaScript": 3571
    },
    "contributions_by_user": 12,
    "contribution_score": 129.74,
    "S_code": 3.49,
    "S_social": 4,
    "S_maint": 12
  },
  {
    "name": "node-colombia",
    "full_name": "DiegoRBaquero/node-colombia",
    "html_url": "https://github.com/DiegoRBaquero/node-colombia",
    "description": "Colombia como módulo JS",
    "stars": 2,
    "forks": 0,
    "languages": {},
    "contributions_by_user": 2,
    "contribution_score": 24.0,
    "S_code": 0.0,
    "S_social": 2,
    "S_maint": 2
  },
  {
    "name": "js-libp2p-webrtc-multti",
    "full_name": "DiegoRBaquero/js-libp2p-webrtc-multti",
    "html_url": "https://github.com/DiegoRBaquero/js-libp2p-webrtc-multti",
    "description": "libp2p WebRTC transport that includes a discovery mechanism provided by the signalling-multti",
    "stars": 2,
    "forks": 0,
    "languages": {
      "TypeScript": 73970,
      "JavaScript": 2963,
      "HTML": 2049,
      "Dockerfile": 410
    },
    "contributions_by_user": 0,
    "contribution_score": 42.77,
    "S_code": 77.53,
    "S_social": 2,
    "S_maint": 0
  },
  {
    "name": "ftp-srv",
    "full_name": "DiegoRBaquero/ftp-srv",
    "html_url": "https://github.com/DiegoRBaquero/ftp-srv",
    "description": ":postbox: Modern FTP Server",
    "stars": 2,
    "forks": 0,
    "languages": {
      "JavaScript": 152772,
      "HTML": 1493
    },
    "contributions_by_user": 0,
    "contribution_score": 79.32,
    "S_code": 150.65,
    "S_social": 2,
    "S_maint": 0
  },
  {
    "name": "express-debug-async-wrap",
    "full_name": "DiegoRBaquero/express-debug-async-wrap",
    "html_url": "https://github.com/DiegoRBaquero/express-debug-async-wrap",
    "description": "express async wrapper that passes custom debug instance",
    "stars": 2,
    "forks": 1,
    "languages": {
      "JavaScript": 160
    },
    "contributions_by_user": 15,
    "contribution_score": 158.08,
    "S_code": 0.16,
    "S_social": 4,
    "S_maint": 15
  },
  {
    "name": "express-sequelize-crud-router",
    "full_name": "DiegoRBaquero/express-sequelize-crud-router",
    "html_url": "https://github.com/DiegoRBaquero/express-sequelize-crud-router",
    "description": "express CRUD router based on a sequelize model",
    "stars": 2,
    "forks": 0,
    "languages": {
      "JavaScript": 1463
    },
    "contributions_by_user": 10,
    "contribution_score": 104.71,
    "S_code": 1.43,
    "S_social": 2,
    "S_maint": 10
  },
  {
    "name": "logger",
    "full_name": "DiegoRBaquero/logger",
    "html_url": "https://github.com/DiegoRBaquero/logger",
    "description": "Logger library for new (and old) projects",
    "stars": 2,
    "forks": 0,
    "languages": {
      "JavaScript": 29739
    },
    "contributions_by_user": 8,
    "contribution_score": 98.52,
    "S_code": 29.04,
    "S_social": 2,
    "S_maint": 8
  },
  {
    "name": "node-dinli",
    "full_name": "DiegoRBaquero/node-dinli",
    "html_url": "https://github.com/DiegoRBaquero/node-dinli",
    "description": "Wrapper for the Dinli URL Shortener",
    "stars": 2,
    "forks": 0,
    "languages": {
      "JavaScript": 826
    },
    "contributions_by_user": 6,
    "contribution_score": 64.4,
    "S_code": 0.81,
    "S_social": 2,
    "S_maint": 6
  },
  {
    "name": "sequelize-express-findbyid",
    "full_name": "DiegoRBaquero/sequelize-express-findbyid",
    "html_url": "https://github.com/DiegoRBaquero/sequelize-express-findbyid",
    "description": "Find by id using a sequelize model, returning 404 error if not found",
    "stars": 2,
    "forks": 0,
    "languages": {
      "JavaScript": 383
    },
    "contributions_by_user": 20,
    "contribution_score": 204.19,
    "S_code": 0.37,
    "S_social": 2,
    "S_maint": 20
  },
  {
    "name": "diegorbaquero.com",
    "full_name": "DiegoRBaquero/diegorbaquero.com",
    "html_url": "https://github.com/DiegoRBaquero/diegorbaquero.com",
    "description": "Personal cover card",
    "stars": 1,
    "forks": 0,
    "languages": {
      "Ruby": 304
    },
    "contributions_by_user": 22,
    "contribution_score": 222.15,
    "S_code": 0.3,
    "S_social": 1,
    "S_maint": 22
  },
  {
    "name": "jsdelivr",
    "full_name": "DiegoRBaquero/jsdelivr",
    "html_url": "https://github.com/DiegoRBaquero/jsdelivr",
    "description": "A free Open Source CDN for webmasters and developers",
    "stars": 1,
    "forks": 0,
    "languages": {},
    "contributions_by_user": 0,
    "contribution_score": 2.0,
    "S_code": 0.0,
    "S_social": 1,
    "S_maint": 0
  },
  {
    "name": "atlantis",
    "full_name": "DiegoRBaquero/atlantis",
    "html_url": "https://github.com/DiegoRBaquero/atlantis",
    "description": "Terraform Pull Request Automation",
    "stars": 1,
    "forks": 0,
    "languages": {
      "Go": 1778319,
      "Vue": 11409,
      "CSS": 6946,
      "Shell": 6068,
      "Dockerfile": 5378,
      "JavaScript": 5046,
      "HCL": 4348,
      "Makefile": 4170,
      "Stylus": 659
    },
    "contributions_by_user": 0,
    "contribution_score": 891.82,
    "S_code": 1779.63,
    "S_social": 1,
    "S_maint": 0
  },
  {
    "name": "react-pdf",
    "full_name": "DiegoRBaquero/react-pdf",
    "html_url": "https://github.com/DiegoRBaquero/react-pdf",
    "description": "📄  Create PDF files using React",
    "stars": 1,
    "forks": 0,
    "languages": {
      "JavaScript": 2669271,
      "Shell": 634
    },
    "contributions_by_user": 0,
    "contribution_score": 1305.66,
    "S_code": 2607.33,
    "S_social": 1,
    "S_maint": 0
  },
  {
    "name": "tplink-cloud-api",
    "full_name": "DiegoRBaquero/tplink-cloud-api",
    "html_url": "https://github.com/DiegoRBaquero/tplink-cloud-api",
    "description": "A node.js npm module to remotely control TP-Link smartplugs (HS100, HS110) and smartbulbs (LB100, LB110, LB120, LB130) using their cloud web service (no need to be on the same wifi/lan)",
    "stars": 1,
    "forks": 0,
    "languages": {
      "JavaScript": 13191
    },
    "contributions_by_user": 0,
    "contribution_score": 8.44,
    "S_code": 12.88,
    "S_social": 1,
    "S_maint": 0
  },
  {
    "name": "docker-nginx",
    "full_name": "DiegoRBaquero/docker-nginx",
    "html_url": "https://github.com/DiegoRBaquero/docker-nginx",
    "description": "Official NGINX Dockerfiles",
    "stars": 1,
    "forks": 0,
    "languages": {
      "Shell": 89878,
      "Dockerfile": 48464
    },
    "contributions_by_user": 0,
    "contribution_score": 69.55,
    "S_code": 135.1,
    "S_social": 1,
    "S_maint": 0
  },
  {
    "name": "depcheck",
    "full_name": "DiegoRBaquero/depcheck",
    "html_url": "https://github.com/DiegoRBaquero/depcheck",
    "description": "Check your npm module for unused dependencies",
    "stars": 1,
    "forks": 0,
    "languages": {
      "JavaScript": 211928,
      "TypeScript": 894,
      "Vue": 486,
      "SCSS": 303,
      "Sass": 300,
      "Svelte": 74,
      "CoffeeScript": 59
    },
    "contributions_by_user": 0,
    "contribution_score": 106.51,
    "S_code": 209.03,
    "S_social": 1,
    "S_maint": 0
  },
  {
    "name": "terraform-aws-lambda-builder",
    "full_name": "DiegoRBaquero/terraform-aws-lambda-builder",
    "html_url": "https://github.com/DiegoRBaquero/terraform-aws-lambda-builder",
    "description": "Terraform module to build Lambda functions in Lambda or CodeBuild",
    "stars": 1,
    "forks": 0,
    "languages": {
      "HCL": 25861,
      "Python": 21420,
      "JavaScript": 4302,
      "Makefile": 1238,
      "Go": 625,
      "Shell": 267
    },
    "contributions_by_user": 0,
    "contribution_score": 28.23,
    "S_code": 52.45,
    "S_social": 1,
    "S_maint": 0
  },
  {
    "name": "eslint-config-ipfs",
    "full_name": "DiegoRBaquero/eslint-config-ipfs",
    "html_url": "https://github.com/DiegoRBaquero/eslint-config-ipfs",
    "description": "An ESLint Shareable Config used by IPFS project",
    "stars": 1,
    "forks": 0,
    "languages": {
      "JavaScript": 4684
    },
    "contributions_by_user": 0,
    "contribution_score": 4.29,
    "S_code": 4.57,
    "S_social": 1,
    "S_maint": 0
  },
  {
    "name": "renovate",
    "full_name": "DiegoRBaquero/renovate",
    "html_url": "https://github.com/DiegoRBaquero/renovate",
    "description": "Universal dependency update tool that fits into your workflows.",
    "stars": 1,
    "forks": 0,
    "languages": {
      "TypeScript": 3866787,
      "HTML": 134227,
      "Clojure": 30629,
      "Swift": 30469,
      "JavaScript": 18342,
      "Ruby": 13627,
      "HCL": 13206,
      "Dockerfile": 10024,
      "Starlark": 8414,
      "Python": 6721,
      "Scala": 3253,
      "Shell": 1352,
      "Roff": 642,
      "Elixir": 537,
      "CoffeeScript": 437
    },
    "contributions_by_user": 0,
    "contribution_score": 2022.83,
    "S_code": 4041.67,
    "S_social": 1,
    "S_maint": 0
  },
  {
    "name": "node-1",
    "full_name": "DiegoRBaquero/node-1",
    "html_url": "https://github.com/DiegoRBaquero/node-1",
    "description": "Official Node client library for IPinfo API (IP geolocation and other types of IP data)",
    "stars": 1,
    "forks": 0,
    "languages": {
      "TypeScript": 30453,
      "JavaScript": 928,
      "Shell": 752
    },
    "contributions_by_user": 0,
    "contribution_score": 17.69,
    "S_code": 31.38,
    "S_social": 1,
    "S_maint": 0
  },
  {
    "name": "renovate-config",
    "full_name": "DiegoRBaquero/renovate-config",
    "html_url": "https://github.com/DiegoRBaquero/renovate-config",
    "description": "Base renovate config",
    "stars": 1,
    "forks": 1,
    "languages": {},
    "contributions_by_user": 10,
    "contribution_score": 106.0,
    "S_code": 0.0,
    "S_social": 3,
    "S_maint": 10
  },
  {
    "name": "launchpad",
    "full_name": "DiegoRBaquero/launchpad",
    "html_url": "https://github.com/DiegoRBaquero/launchpad",
    "description": "The curriculum for the Launchpad program",
    "stars": 1,
    "forks": 0,
    "languages": {},
    "contributions_by_user": 0,
    "contribution_score": 2.0,
    "S_code": 0.0,
    "S_social": 1,
    "S_maint": 0
  },
  {
    "name": "taller6-pruebas-automaticas",
    "full_name": "DiegoRBaquero/taller6-pruebas-automaticas",
    "html_url": "https://github.com/DiegoRBaquero/taller6-pruebas-automaticas",
    "description": null,
    "stars": 1,
    "forks": 0,
    "languages": {
      "JavaScript": 13535,
      "Gherkin": 1720
    },
    "contributions_by_user": 2,
    "contribution_score": 29.45,
    "S_code": 14.9,
    "S_social": 1,
    "S_maint": 2
  },
  {
    "name": "taller7-pruebas-automaticas",
    "full_name": "DiegoRBaquero/taller7-pruebas-automaticas",
    "html_url": "https://github.com/DiegoRBaquero/taller7-pruebas-automaticas",
    "description": null,
    "stars": 1,
    "forks": 0,
    "languages": {
      "Java": 5054372,
      "JavaScript": 229420,
      "PLpgSQL": 34049,
      "CSS": 13147,
      "Python": 12470,
      "Shell": 10550,
      "XSLT": 7113,
      "HTML": 6421
    },
    "contributions_by_user": 8,
    "contribution_score": 2702.87,
    "S_code": 5241.74,
    "S_social": 1,
    "S_maint": 8
  },
  {
    "name": "thank-you-github",
    "full_name": "DiegoRBaquero/thank-you-github",
    "html_url": "https://github.com/DiegoRBaquero/thank-you-github",
    "description": "An open letter of gratitude to GitHub",
    "stars": 1,
    "forks": 1,
    "languages": {},
    "contributions_by_user": 0,
    "contribution_score": 6.0,
    "S_code": 0.0,
    "S_social": 3,
    "S_maint": 0
  },
  {
    "name": "serempre-msg",
    "full_name": "DiegoRBaquero/serempre-msg",
    "html_url": "https://github.com/DiegoRBaquero/serempre-msg",
    "description": null,
    "stars": 0,
    "forks": 0,
    "languages": {
      "JavaScript": 1530
    },
    "contributions_by_user": 0,
    "contribution_score": 0.75,
    "S_code": 1.49,
    "S_social": 0,
    "S_maint": 0
  },
  {
    "name": "shepherd",
    "full_name": "DiegoRBaquero/shepherd",
    "html_url": "https://github.com/DiegoRBaquero/shepherd",
    "description": "A utility for applying code changes across many repositories.",
    "stars": 0,
    "forks": 0,
    "languages": {
      "TypeScript": 55420,
      "JavaScript": 6856
    },
    "contributions_by_user": 0,
    "contribution_score": 30.41,
    "S_code": 60.82,
    "S_social": 0,
    "S_maint": 0
  },
  {
    "name": "s3-action",
    "full_name": "DiegoRBaquero/s3-action",
    "html_url": "https://github.com/DiegoRBaquero/s3-action",
    "description": "☕ Simple GitHub action to upload contents from a GitHub repository to a S3 bucket, supports AWS and Wasabi",
    "stars": 0,
    "forks": 0,
    "languages": {
      "TypeScript": 39709,
      "JavaScript": 3686
    },
    "contributions_by_user": 0,
    "contribution_score": 21.19,
    "S_code": 42.38,
    "S_social": 0,
    "S_maint": 0
  },
  {
    "name": "split-ref",
    "full_name": "DiegoRBaquero/split-ref",
    "html_url": "https://github.com/DiegoRBaquero/split-ref",
    "description": null,
    "stars": 0,
    "forks": 0,
    "languages": {},
    "contributions_by_user": 3,
    "contribution_score": 30.0,
    "S_code": 0.0,
    "S_social": 0,
    "S_maint": 3
  },
  {
    "name": "tlsn-extension",
    "full_name": "DiegoRBaquero/tlsn-extension",
    "html_url": "https://github.com/DiegoRBaquero/tlsn-extension",
    "description": "Chrome Extension for TLSNotary",
    "stars": 0,
    "forks": 0,
    "languages": {
      "TypeScript": 104999,
      "JavaScript": 10136,
      "SCSS": 3383,
      "HTML": 759,
      "CSS": 628
    },
    "contributions_by_user": 0,
    "contribution_score": 58.55,
    "S_code": 117.09,
    "S_social": 0,
    "S_maint": 0
  },
  {
    "name": "taller9-pruebas-automaticas",
    "full_name": "DiegoRBaquero/taller9-pruebas-automaticas",
    "html_url": "https://github.com/DiegoRBaquero/taller9-pruebas-automaticas",
    "description": null,
    "stars": 0,
    "forks": 0,
    "languages": {
      "HTML": 229386,
      "JavaScript": 226328,
      "CSS": 2402
    },
    "contributions_by_user": 1,
    "contribution_score": 233.69,
    "S_code": 447.38,
    "S_social": 0,
    "S_maint": 1
  },
  {
    "name": "node",
    "full_name": "DiegoRBaquero/node",
    "html_url": "https://github.com/DiegoRBaquero/node",
    "description": "Node.js JavaScript runtime :sparkles::turtle::rocket::sparkles:",
    "stars": 0,
    "forks": 0,
    "languages": {
      "JavaScript": 5917253,
      "C++": 2101583,
      "C": 407678,
      "HTML": 163390,
      "Python": 92347,
      "PHP": 88241,
      "Makefile": 38581,
      "DTrace": 37661,
      "Batchfile": 24802,
      "Roff": 15312,
      "R": 5359,
      "Shell": 1944
    },
    "contributions_by_user": 0,
    "contribution_score": 4342.85,
    "S_code": 8685.69,
    "S_social": 0,
    "S_maint": 0
  },
  {
    "name": "memo-async-lru",
    "full_name": "DiegoRBaquero/memo-async-lru",
    "html_url": "https://github.com/DiegoRBaquero/memo-async-lru",
    "description": "Memoize Node.js style callback-last functions, using an in-memory LRU store",
    "stars": 0,
    "forks": 0,
    "languages": {
      "JavaScript": 2797
    },
    "contributions_by_user": 0,
    "contribution_score": 1.37,
    "S_code": 2.73,
    "S_social": 0,
    "S_maint": 0
  },
  {
    "name": "bull",
    "full_name": "DiegoRBaquero/bull",
    "html_url": "https://github.com/DiegoRBaquero/bull",
    "description": "Premium Queue package for handling distributed jobs and messages in NodeJS.",
    "stars": 0,
    "forks": 0,
    "languages": {
      "JavaScript": 270893,
      "Lua": 26108
    },
    "contributions_by_user": 0,
    "contribution_score": 145.02,
    "S_code": 290.04,
    "S_social": 0,
    "S_maint": 0
  },
  {
    "name": "sqs-consumer",
    "full_name": "DiegoRBaquero/sqs-consumer",
    "html_url": "https://github.com/DiegoRBaquero/sqs-consumer",
    "description": "Build SQS-based Node applications without the boilerplate",
    "stars": 0,
    "forks": 0,
    "languages": {
      "JavaScript": 20184
    },
    "contributions_by_user": 0,
    "contribution_score": 9.86,
    "S_code": 19.71,
    "S_social": 0,
    "S_maint": 0
  },
  {
    "name": "lts",
    "full_name": "DiegoRBaquero/lts",
    "html_url": "https://github.com/DiegoRBaquero/lts",
    "description": "Generate the Node.js LTS schedule",
    "stars": 0,
    "forks": 0,
    "languages": {
      "JavaScript": 7907
    },
    "contributions_by_user": 0,
    "contribution_score": 3.86,
    "S_code": 7.72,
    "S_social": 0,
    "S_maint": 0
  },
  {
    "name": "board",
    "full_name": "DiegoRBaquero/board",
    "html_url": "https://github.com/DiegoRBaquero/board",
    "description": "The Node Foundation Board of Directors",
    "stars": 0,
    "forks": 0,
    "languages": {
      "JavaScript": 1405
    },
    "contributions_by_user": 0,
    "contribution_score": 0.69,
    "S_code": 1.37,
    "S_social": 0,
    "S_maint": 0
  },
  {
    "name": "yargs",
    "full_name": "DiegoRBaquero/yargs",
    "html_url": "https://github.com/DiegoRBaquero/yargs",
    "description": " yargs the modern, pirate-themed successor to optimist.",
    "stars": 0,
    "forks": 0,
    "languages": {
      "JavaScript": 353973,
      "HTML": 775
    },
    "contributions_by_user": 0,
    "contribution_score": 173.22,
    "S_code": 346.43,
    "S_social": 0,
    "S_maint": 0
  },
  {
    "name": "r2",
    "full_name": "DiegoRBaquero/r2",
    "html_url": "https://github.com/DiegoRBaquero/r2",
    "description": "HTTP client. Spiritual successor to request.",
    "stars": 0,
    "forks": 0,
    "languages": {
      "JavaScript": 9173
    },
    "contributions_by_user": 0,
    "contribution_score": 4.48,
    "S_code": 8.96,
    "S_social": 0,
    "S_maint": 0
  },
  {
    "name": "lab",
    "full_name": "DiegoRBaquero/lab",
    "html_url": "https://github.com/DiegoRBaquero/lab",
    "description": "Node test utility",
    "stars": 0,
    "forks": 0,
    "languages": {
      "JavaScript": 421356,
      "HTML": 16699,
      "TypeScript": 2801,
      "C++": 303
    },
    "contributions_by_user": 0,
    "contribution_score": 215.41,
    "S_code": 430.82,
    "S_social": 0,
    "S_maint": 0
  },
  {
    "name": "eslint-config-hapi",
    "full_name": "DiegoRBaquero/eslint-config-hapi",
    "html_url": "https://github.com/DiegoRBaquero/eslint-config-hapi",
    "description": "Shareable ESLint config for the hapi ecosystem",
    "stars": 0,
    "forks": 0,
    "languages": {
      "JavaScript": 29398
    },
    "contributions_by_user": 0,
    "contribution_score": 14.35,
    "S_code": 28.71,
    "S_social": 0,
    "S_maint": 0
  },
  {
    "name": "mongoose",
    "full_name": "DiegoRBaquero/mongoose",
    "html_url": "https://github.com/DiegoRBaquero/mongoose",
    "description": "MongoDB object modeling designed to work in an asynchronous environment.",
    "stars": 0,
    "forks": 0,
    "languages": {
      "JavaScript": 3422047,
      "HTML": 31251,
      "Makefile": 1184
    },
    "contributions_by_user": 0,
    "contribution_score": 1686.76,
    "S_code": 3373.52,
    "S_social": 0,
    "S_maint": 0
  },
  {
    "name": "body-parser",
    "full_name": "DiegoRBaquero/body-parser",
    "html_url": "https://github.com/DiegoRBaquero/body-parser",
    "description": "Node.js body parsing middleware",
    "stars": 0,
    "forks": 0,
    "languages": {
      "JavaScript": 96168
    },
    "contributions_by_user": 0,
    "contribution_score": 46.96,
    "S_code": 93.91,
    "S_social": 0,
    "S_maint": 0
  },
  {
    "name": "moment",
    "full_name": "DiegoRBaquero/moment",
    "html_url": "https://github.com/DiegoRBaquero/moment",
    "description": "Parse, validate, manipulate, and display dates in javascript.",
    "stars": 0,
    "forks": 0,
    "languages": {
      "JavaScript": 8563313,
      "TypeScript": 13702,
      "Shell": 739
    },
    "contributions_by_user": 0,
    "contribution_score": 4188.36,
    "S_code": 8376.71,
    "S_social": 0,
    "S_maint": 0
  },
  {
    "name": "event-sourcerer-client",
    "full_name": "DiegoRBaquero/event-sourcerer-client",
    "html_url": "https://github.com/DiegoRBaquero/event-sourcerer-client",
    "description": null,
    "stars": 0,
    "forks": 0,
    "languages": {
      "JavaScript": 18719
    },
    "contributions_by_user": 4,
    "contribution_score": 49.14,
    "S_code": 18.28,
    "S_social": 0,
    "S_maint": 4
  },
  {
    "name": "gremlins.js",
    "full_name": "DiegoRBaquero/gremlins.js",
    "html_url": "https://github.com/DiegoRBaquero/gremlins.js",
    "description": "Monkey testing library for web apps and Node.js",
    "stars": 0,
    "forks": 0,
    "languages": {
      "JavaScript": 73502,
      "HTML": 552,
      "Makefile": 194
    },
    "contributions_by_user": 0,
    "contribution_score": 36.25,
    "S_code": 72.51,
    "S_social": 0,
    "S_maint": 0
  },
  {
    "name": "sequelize",
    "full_name": "DiegoRBaquero/sequelize",
    "html_url": "https://github.com/DiegoRBaquero/sequelize",
    "description": "Feature-rich ORM for modern Node.js and TypeScript, it supports PostgreSQL (with JSON and JSONB support), MySQL, MariaDB, SQLite, MS SQL Server, Snowflake, Oracle DB (v6), DB2 and DB2 for IBM i.",
    "stars": 0,
    "forks": 0,
    "languages": {
      "JavaScript": 2846728,
      "TypeScript": 1569615,
      "Shell": 11719
    },
    "contributions_by_user": 0,
    "contribution_score": 2162.14,
    "S_code": 4324.28,
    "S_social": 0,
    "S_maint": 0
  },
  {
    "name": "multer",
    "full_name": "DiegoRBaquero/multer",
    "html_url": "https://github.com/DiegoRBaquero/multer",
    "description": "Node.js middleware for handling `multipart/form-data`.",
    "stars": 0,
    "forks": 0,
    "languages": {
      "JavaScript": 53308
    },
    "contributions_by_user": 0,
    "contribution_score": 26.03,
    "S_code": 52.06,
    "S_social": 0,
    "S_maint": 0
  },
  {
    "name": "hapi-redis",
    "full_name": "DiegoRBaquero/hapi-redis",
    "html_url": "https://github.com/DiegoRBaquero/hapi-redis",
    "description": "You've got redis on my hapi",
    "stars": 0,
    "forks": 0,
    "languages": {
      "JavaScript": 4107
    },
    "contributions_by_user": 1,
    "contribution_score": 12.01,
    "S_code": 4.01,
    "S_social": 0,
    "S_maint": 1
  },
  {
    "name": "node-googl",
    "full_name": "DiegoRBaquero/node-googl",
    "html_url": "https://github.com/DiegoRBaquero/node-googl",
    "description": "A Node.js url shortener and expander powered by Google",
    "stars": 0,
    "forks": 0,
    "languages": {
      "JavaScript": 13200
    },
    "contributions_by_user": 0,
    "contribution_score": 6.45,
    "S_code": 12.89,
    "S_social": 0,
    "S_maint": 0
  },
  {
    "name": "eslint-plugin-hapi",
    "full_name": "DiegoRBaquero/eslint-plugin-hapi",
    "html_url": "https://github.com/DiegoRBaquero/eslint-plugin-hapi",
    "description": "ESLint plugin containing hapi style guide rules",
    "stars": 0,
    "forks": 0,
    "languages": {
      "JavaScript": 1382
    },
    "contributions_by_user": 0,
    "contribution_score": 0.67,
    "S_code": 1.35,
    "S_social": 0,
    "S_maint": 0
  },
  {
    "name": "mediasource",
    "full_name": "DiegoRBaquero/mediasource",
    "html_url": "https://github.com/DiegoRBaquero/mediasource",
    "description": "MediaSource API as a node.js Writable stream",
    "stars": 0,
    "forks": 0,
    "languages": {
      "JavaScript": 10186
    },
    "contributions_by_user": 0,
    "contribution_score": 4.97,
    "S_code": 9.95,
    "S_social": 0,
    "S_maint": 0
  },
  {
    "name": "underscore",
    "full_name": "DiegoRBaquero/underscore",
    "html_url": "https://github.com/DiegoRBaquero/underscore",
    "description": "JavaScript's utility _ belt",
    "stars": 0,
    "forks": 0,
    "languages": {
      "JavaScript": 240976,
      "HTML": 140909
    },
    "contributions_by_user": 0,
    "contribution_score": 186.47,
    "S_code": 372.93,
    "S_social": 0,
    "S_maint": 0
  },
  {
    "name": "standard",
    "full_name": "DiegoRBaquero/standard",
    "html_url": "https://github.com/DiegoRBaquero/standard",
    "description": "🌟 JavaScript Style Guide, with linter & automatic code fixer",
    "stars": 0,
    "forks": 0,
    "languages": {
      "JavaScript": 5305,
      "Shell": 573
    },
    "contributions_by_user": 0,
    "contribution_score": 2.87,
    "S_code": 5.74,
    "S_social": 0,
    "S_maint": 0
  },
  {
    "name": "doc-pm2",
    "full_name": "DiegoRBaquero/doc-pm2",
    "html_url": "https://github.com/DiegoRBaquero/doc-pm2",
    "description": "PM2 documentation",
    "stars": 0,
    "forks": 0,
    "languages": {
      "CSS": 42539,
      "HTML": 15332,
      "JavaScript": 10873,
      "Ruby": 2184,
      "Dockerfile": 452
    },
    "contributions_by_user": 0,
    "contribution_score": 34.85,
    "S_code": 69.71,
    "S_social": 0,
    "S_maint": 0
  },
  {
    "name": "node-pool",
    "full_name": "DiegoRBaquero/node-pool",
    "html_url": "https://github.com/DiegoRBaquero/node-pool",
    "description": "Generic resource pooling for node.js",
    "stars": 0,
    "forks": 0,
    "languages": {
      "JavaScript": 67963,
      "Makefile": 156
    },
    "contributions_by_user": 0,
    "contribution_score": 33.26,
    "S_code": 66.52,
    "S_social": 0,
    "S_maint": 0
  },
  {
    "name": "puppeteer",
    "full_name": "DiegoRBaquero/puppeteer",
    "html_url": "https://github.com/DiegoRBaquero/puppeteer",
    "description": "Headless Chrome Node API",
    "stars": 0,
    "forks": 0,
    "languages": {
      "JavaScript": 460654,
      "HTML": 13300,
      "CSS": 262
    },
    "contributions_by_user": 0,
    "contribution_score": 231.55,
    "S_code": 463.1,
    "S_social": 0,
    "S_maint": 0
  },
  {
    "name": "heavy",
    "full_name": "DiegoRBaquero/heavy",
    "html_url": "https://github.com/DiegoRBaquero/heavy",
    "description": ":office: Measure process load",
    "stars": 0,
    "forks": 0,
    "languages": {
      "JavaScript": 7009
    },
    "contributions_by_user": 0,
    "contribution_score": 3.42,
    "S_code": 6.84,
    "S_social": 0,
    "S_maint": 0
  },
  {
    "name": "debug",
    "full_name": "DiegoRBaquero/debug",
    "html_url": "https://github.com/DiegoRBaquero/debug",
    "description": "A tiny JavaScript debugging utility modelled after Node.js core's debugging technique. Works in Node.js and web browsers",
    "stars": 0,
    "forks": 0,
    "languages": {
      "JavaScript": 18790,
      "Makefile": 1234
    },
    "contributions_by_user": 0,
    "contribution_score": 9.78,
    "S_code": 19.55,
    "S_social": 0,
    "S_maint": 0
  },
  {
    "name": "chunk-store-stream",
    "full_name": "DiegoRBaquero/chunk-store-stream",
    "html_url": "https://github.com/DiegoRBaquero/chunk-store-stream",
    "description": "Convert an abstract-chunk-store compliant store into a readable or writable stream",
    "stars": 0,
    "forks": 0,
    "languages": {
      "JavaScript": 4826
    },
    "contributions_by_user": 0,
    "contribution_score": 2.36,
    "S_code": 4.71,
    "S_social": 0,
    "S_maint": 0
  },
  {
    "name": "dx-nodejs",
    "full_name": "DiegoRBaquero/dx-nodejs",
    "html_url": "https://github.com/DiegoRBaquero/dx-nodejs",
    "description": "MercadoPago SDK Node.js - Developer Experience",
    "stars": 0,
    "forks": 0,
    "languages": {
      "JavaScript": 184914
    },
    "contributions_by_user": 0,
    "contribution_score": 90.29,
    "S_code": 180.58,
    "S_social": 0,
    "S_maint": 0
  },
  {
    "name": "hapi-pino",
    "full_name": "DiegoRBaquero/hapi-pino",
    "html_url": "https://github.com/DiegoRBaquero/hapi-pino",
    "description": "🌲 Hapi plugin for the Pino logger",
    "stars": 0,
    "forks": 0,
    "languages": {
      "JavaScript": 41861
    },
    "contributions_by_user": 0,
    "contribution_score": 20.44,
    "S_code": 40.88,
    "S_social": 0,
    "S_maint": 0
  },
  {
    "name": "cajero-aspectos",
    "full_name": "DiegoRBaquero/cajero-aspectos",
    "html_url": "https://github.com/DiegoRBaquero/cajero-aspectos",
    "description": null,
    "stars": 0,
    "forks": 0,
    "languages": {
      "Java": 12881,
      "AspectJ": 5726
    },
    "contributions_by_user": 0,
    "contribution_score": 9.09,
    "S_code": 18.17,
    "S_social": 0,
    "S_maint": 0
  },
  {
    "name": "jackrabbit",
    "full_name": "DiegoRBaquero/jackrabbit",
    "html_url": "https://github.com/DiegoRBaquero/jackrabbit",
    "description": "Simple AMQP / RabbitMQ job queues for node based on amqplib",
    "stars": 0,
    "forks": 0,
    "languages": {
      "JavaScript": 37064,
      "Dockerfile": 448
    },
    "contributions_by_user": 2,
    "contribution_score": 38.32,
    "S_code": 36.63,
    "S_social": 0,
    "S_maint": 2
  },
  {
    "name": "grafos-lib",
    "full_name": "DiegoRBaquero/grafos-lib",
    "html_url": "https://github.com/DiegoRBaquero/grafos-lib",
    "description": null,
    "stars": 0,
    "forks": 0,
    "languages": {
      "Java": 8563
    },
    "contributions_by_user": 0,
    "contribution_score": 4.18,
    "S_code": 8.36,
    "S_social": 0,
    "S_maint": 0
  },
  {
    "name": "minion-army",
    "full_name": "DiegoRBaquero/minion-army",
    "html_url": "https://github.com/DiegoRBaquero/minion-army",
    "description": "Microservice Framework for RabbitMQ Workers",
    "stars": 0,
    "forks": 0,
    "languages": {
      "JavaScript": 15198
    },
    "contributions_by_user": 8,
    "contribution_score": 87.42,
    "S_code": 14.84,
    "S_social": 0,
    "S_maint": 8
  },
  {
    "name": "minion",
    "full_name": "DiegoRBaquero/minion",
    "html_url": "https://github.com/DiegoRBaquero/minion",
    "description": "Microservice Framework for RabbitMQ Workers",
    "stars": 0,
    "forks": 0,
    "languages": {
      "JavaScript": 15386
    },
    "contributions_by_user": 5,
    "contribution_score": 57.51,
    "S_code": 15.03,
    "S_social": 0,
    "S_maint": 5
  },
  {
    "name": "taller5-pruebas-automaticas",
    "full_name": "DiegoRBaquero/taller5-pruebas-automaticas",
    "html_url": "https://github.com/DiegoRBaquero/taller5-pruebas-automaticas",
    "description": null,
    "stars": 0,
    "forks": 0,
    "languages": {
      "JavaScript": 16144,
      "Shell": 252
    },
    "contributions_by_user": 2,
    "contribution_score": 28.01,
    "S_code": 16.01,
    "S_social": 0,
    "S_maint": 2
  },
  {
    "name": "frontstepbystep",
    "full_name": "DiegoRBaquero/frontstepbystep",
    "html_url": "https://github.com/DiegoRBaquero/frontstepbystep",
    "description": null,
    "stars": 0,
    "forks": 0,
    "languages": {
      "TypeScript": 97670,
      "HTML": 36469,
      "JavaScript": 1924,
      "CSS": 538
    },
    "contributions_by_user": 7,
    "contribution_score": 136.7,
    "S_code": 133.4,
    "S_social": 0,
    "S_maint": 7
  },
  {
    "name": "taller2-pruebas-automaticas",
    "full_name": "DiegoRBaquero/taller2-pruebas-automaticas",
    "html_url": "https://github.com/DiegoRBaquero/taller2-pruebas-automaticas",
    "description": null,
    "stars": 0,
    "forks": 0,
    "languages": {
      "JavaScript": 24228,
      "TypeScript": 18431,
      "CSS": 3657,
      "HTML": 1946
    },
    "contributions_by_user": 3,
    "contribution_score": 53.57,
    "S_code": 47.13,
    "S_social": 0,
    "S_maint": 3
  },
  {
    "name": "taller3-pruebas-automaticas",
    "full_name": "DiegoRBaquero/taller3-pruebas-automaticas",
    "html_url": "https://github.com/DiegoRBaquero/taller3-pruebas-automaticas",
    "description": null,
    "stars": 0,
    "forks": 0,
    "languages": {
      "JavaScript": 2750
    },
    "contributions_by_user": 1,
    "contribution_score": 11.34,
    "S_code": 2.69,
    "S_social": 0,
    "S_maint": 1
  },
  {
    "name": "hackathon-scotia",
    "full_name": "DiegoRBaquero/hackathon-scotia",
    "html_url": "https://github.com/DiegoRBaquero/hackathon-scotia",
    "description": null,
    "stars": 0,
    "forks": 0,
    "languages": {
      "JavaScript": 47570,
      "Dockerfile": 120
    },
    "contributions_by_user": 9,
    "contribution_score": 113.29,
    "S_code": 46.57,
    "S_social": 0,
    "S_maint": 9
  },
  {
    "name": "taller8-pruebas-automaticas",
    "full_name": "DiegoRBaquero/taller8-pruebas-automaticas",
    "html_url": "https://github.com/DiegoRBaquero/taller8-pruebas-automaticas",
    "description": null,
    "stars": 0,
    "forks": 0,
    "languages": {
      "Java": 1226630,
      "Shell": 5806,
      "Makefile": 290
    },
    "contributions_by_user": 1,
    "contribution_score": 611.92,
    "S_code": 1203.83,
    "S_social": 0,
    "S_maint": 1
  },
  {
    "name": "dotfiles",
    "full_name": "DiegoRBaquero/dotfiles",
    "html_url": "https://github.com/DiegoRBaquero/dotfiles",
    "description": "Pager's settings for developers",
    "stars": 0,
    "forks": 0,
    "languages": {
      "Shell": 2628,
      "Ruby": 486
    },
    "contributions_by_user": 1,
    "contribution_score": 11.52,
    "S_code": 3.04,
    "S_social": 0,
    "S_maint": 1
  },
  {
    "name": "front-end-conferences",
    "full_name": "DiegoRBaquero/front-end-conferences",
    "html_url": "https://github.com/DiegoRBaquero/front-end-conferences",
    "description": "This is a list of upcoming front-end related conferences.",
    "stars": 0,
    "forks": 0,
    "languages": {},
    "contributions_by_user": 0,
    "contribution_score": 0.0,
    "S_code": 0.0,
    "S_social": 0,
    "S_maint": 0
  },
  {
    "name": "Visual-JOIN",
    "full_name": "DiegoRBaquero/Visual-JOIN",
    "html_url": "https://github.com/DiegoRBaquero/Visual-JOIN",
    "description": "Understand how joins work by interacting and see it visually",
    "stars": 0,
    "forks": 0,
    "languages": {
      "JavaScript": 16810,
      "HTML": 11969
    },
    "contributions_by_user": 0,
    "contribution_score": 14.05,
    "S_code": 28.1,
    "S_social": 0,
    "S_maint": 0
  },
  {
    "name": "proyecto-agiles",
    "full_name": "DiegoRBaquero/proyecto-agiles",
    "html_url": "https://github.com/DiegoRBaquero/proyecto-agiles",
    "description": null,
    "stars": 0,
    "forks": 2,
    "languages": {
      "Python": 64313,
      "HTML": 48418,
      "CSS": 3340
    },
    "contributions_by_user": 61,
    "contribution_score": 674.68,
    "S_code": 113.35,
    "S_social": 4,
    "S_maint": 61
  },
  {
    "name": "colombia",
    "full_name": "DiegoRBaquero/colombia",
    "html_url": "https://github.com/DiegoRBaquero/colombia",
    "description": "NodeConf Colombia",
    "stars": 0,
    "forks": 0,
    "languages": {
      "CSS": 27754,
      "HTML": 6719,
      "JavaScript": 7
    },
    "contributions_by_user": 0,
    "contribution_score": 16.84,
    "S_code": 33.67,
    "S_social": 0,
    "S_maint": 0
  },
  {
    "name": "web-conferences-2018",
    "full_name": "DiegoRBaquero/web-conferences-2018",
    "html_url": "https://github.com/DiegoRBaquero/web-conferences-2018",
    "description": "A list of Web & JavaScript related conferences happening in 2018.",
    "stars": 0,
    "forks": 0,
    "languages": {},
    "contributions_by_user": 0,
    "contribution_score": 0.0,
    "S_code": 0.0,
    "S_social": 0,
    "S_maint": 0
  },
  {
    "name": "hexo-theme-again",
    "full_name": "DiegoRBaquero/hexo-theme-again",
    "html_url": "https://github.com/DiegoRBaquero/hexo-theme-again",
    "description": "lalala",
    "stars": 0,
    "forks": 0,
    "languages": {
      "CSS": 11322,
      "HTML": 6090,
      "JavaScript": 724
    },
    "contributions_by_user": 0,
    "contribution_score": 8.86,
    "S_code": 17.71,
    "S_social": 0,
    "S_maint": 0
  },
  {
    "name": "Bitacora-Pruebas-Automaticas",
    "full_name": "DiegoRBaquero/Bitacora-Pruebas-Automaticas",
    "html_url": "https://github.com/DiegoRBaquero/Bitacora-Pruebas-Automaticas",
    "description": "Repositorio de bitácora para el curso Pruebas Automáticas - MISO4208",
    "stars": 0,
    "forks": 0,
    "languages": {
      "JavaScript": 2909706,
      "HTML": 577763,
      "CSS": 183864,
      "XSLT": 21531,
      "Ruby": 2319,
      "Gherkin": 1455,
      "Shell": 1450
    },
    "contributions_by_user": 87,
    "contribution_score": 2675.71,
    "S_code": 3611.41,
    "S_social": 0,
    "S_maint": 87
  },
  {
    "name": "certification",
    "full_name": "DiegoRBaquero/certification",
    "html_url": "https://github.com/DiegoRBaquero/certification",
    "description": "Public facing repository to document and update community on Node.js Certified Developer project development",
    "stars": 0,
    "forks": 0,
    "languages": {},
    "contributions_by_user": 0,
    "contribution_score": 0.0,
    "S_code": 0.0,
    "S_social": 0,
    "S_maint": 0
  },
  {
    "name": "taller4-pruebas-automaticas",
    "full_name": "DiegoRBaquero/taller4-pruebas-automaticas",
    "html_url": "https://github.com/DiegoRBaquero/taller4-pruebas-automaticas",
    "description": null,
    "stars": 0,
    "forks": 0,
    "languages": {
      "Java": 8118,
      "HTML": 166
    },
    "contributions_by_user": 3,
    "contribution_score": 34.04,
    "S_code": 8.09,
    "S_social": 0,
    "S_maint": 3
  },
  {
    "name": "pwa-pruebas-automaticas",
    "full_name": "DiegoRBaquero/pwa-pruebas-automaticas",
    "html_url": "https://github.com/DiegoRBaquero/pwa-pruebas-automaticas",
    "description": "Taller 1: Progressive Web Apps (PWA)",
    "stars": 0,
    "forks": 0,
    "languages": {
      "JavaScript": 32392,
      "CSS": 12241,
      "HTML": 6643
    },
    "contributions_by_user": 20,
    "contribution_score": 225.04,
    "S_code": 50.07,
    "S_social": 0,
    "S_maint": 20
  },
  {
    "name": "js-cube-summation",
    "full_name": "DiegoRBaquero/js-cube-summation",
    "html_url": "https://github.com/DiegoRBaquero/js-cube-summation",
    "description": "Interfaz web para el problema Cube Summation",
    "stars": 0,
    "forks": 0,
    "languages": {
      "JavaScript": 3104,
      "HTML": 887
    },
    "contributions_by_user": 7,
    "contribution_score": 71.95,
    "S_code": 3.9,
    "S_social": 0,
    "S_maint": 7
  },
  {
    "name": "BMagnet-Server",
    "full_name": "DiegoRBaquero/BMagnet-Server",
    "html_url": "https://github.com/DiegoRBaquero/BMagnet-Server",
    "description": "Server for BMagnet parsed torrents",
    "stars": 0,
    "forks": 0,
    "languages": {},
    "contributions_by_user": 0,
    "contribution_score": 0.0,
    "S_code": 0.0,
    "S_social": 0,
    "S_maint": 0
  },
  {
    "name": "IC-CASO2",
    "full_name": "DiegoRBaquero/IC-CASO2",
    "html_url": "https://github.com/DiegoRBaquero/IC-CASO2",
    "description": "Caso 2 de Infraestructura Computacional",
    "stars": 0,
    "forks": 0,
    "languages": {
      "Java": 11777
    },
    "contributions_by_user": 6,
    "contribution_score": 65.75,
    "S_code": 11.5,
    "S_social": 0,
    "S_maint": 6
  },
  {
    "name": "EHWeb",
    "full_name": "DiegoRBaquero/EHWeb",
    "html_url": "https://github.com/DiegoRBaquero/EHWeb",
    "description": "Interfaz web de enHueco",
    "stars": 0,
    "forks": 0,
    "languages": {
      "JavaScript": 434693,
      "CSS": 28105,
      "HTML": 22851
    },
    "contributions_by_user": 12,
    "contribution_score": 357.13,
    "S_code": 474.27,
    "S_social": 0,
    "S_maint": 12
  }
]