[
  {
    "name": "packages",
    "full_name": "stuartmorgan-g/packages",
    "html_url": "https://github.com/stuartmorgan-g/packages",
    "description": "A collection of useful packages maintained by the Flutter team",
    "stars": 8,
    "forks": 6,
    "languages": {
      "Dart": 2147331,
      "C++": 114397,
      "CMake": 75725,
      "Objective-C": 42761,
      "Java": 30243,
      "Shell": 28284,
      "HTML": 25619,
      "Swift": 10468,
      "C": 5228,
      "Ruby": 4615,
      "Kotlin": 3369,
      "Dockerfile": 768,
      "Batchfile": 693
    },
    "contributions_by_user": 56,
    "contribution_score": 1815.58,
    "S_code": 2431.15,
    "S_social": 20,
    "S_maint": 56
  },
  {
    "name": "engine",
    "full_name": "stuartmorgan-g/engine",
    "html_url": "https://github.com/stuartmorgan-g/engine",
    "description": "The Flutter engine",
    "stars": 3,
    "forks": 3,
    "languages": {
      "C++": 1500497,
      "Dart": 1137628,
      "Java": 570620,
      "Objective-C++": 316844,
      "Objective-C": 129474,
      "Python": 59168,
      "Roff": 55608,
      "C": 47861,
      "Shell": 14662,
      "Ruby": 758,
      "Dockerfile": 753
    },
    "contributions_by_user": 0,
    "contribution_score": 1890.01,
    "S_code": 3744.02,
    "S_social": 9,
    "S_maint": 0
  },
  {
    "name": "flutter-desktop-embedding",
    "full_name": "stuartmorgan-g/flutter-desktop-embedding",
    "html_url": "https://github.com/stuartmorgan-g/flutter-desktop-embedding",
    "description": "Desktop implementations of the Flutter embedding API",
    "stars": 3,
    "forks": 6,
    "languages": {
      "C++": 115043,
      "Dart": 56737,
      "CMake": 33721,
      "Objective-C": 16822,
      "C": 9888,
      "Objective-C++": 8283,
      "Ruby": 5296,
      "Swift": 3835
    },
    "contributions_by_user": 288,
    "contribution_score": 3031.89,
    "S_code": 243.77,
    "S_social": 15,
    "S_maint": 288
  },
  {
    "name": "flutter",
    "full_name": "stuartmorgan-g/flutter",
    "html_url": "https://github.com/stuartmorgan-g/flutter",
    "description": "Flutter makes it easy and fast to build beautiful mobile apps.",
    "stars": 1,
    "forks": 1,
    "languages": {
      "Dart": 28532892,
      "Java": 69989,
      "Objective-C": 62241,
      "Shell": 54091,
      "Ruby": 21103,
      "Batchfile": 9876,
      "HTML": 8859,
      "Dockerfile": 5177,
      "Swift": 5087,
      "PowerShell": 4817,
      "CSS": 4454,
      "JavaScript": 4051,
      "Kotlin": 3812
    },
    "contributions_by_user": 0,
    "contribution_score": 14061.88,
    "S_code": 28111.77,
    "S_social": 3,
    "S_maint": 0
  },
  {
    "name": "buildroot",
    "full_name": "stuartmorgan-g/buildroot",
    "html_url": "https://github.com/stuartmorgan-g/buildroot",
    "description": "Build environment for the Flutter engine",
    "stars": 1,
    "forks": 1,
    "languages": {
      "Python": 1670766,
      "Shell": 165114,
      "C++": 31316,
      "Java": 23452,
      "sed": 1677,
      "Makefile": 402
    },
    "contributions_by_user": 0,
    "contribution_score": 930.18,
    "S_code": 1848.37,
    "S_social": 3,
    "S_maint": 0
  },
  {
    "name": "samples",
    "full_name": "stuartmorgan-g/samples",
    "html_url": "https://github.com/stuartmorgan-g/samples",
    "description": "A collection of Flutter examples and demos",
    "stars": 1,
    "forks": 0,
    "languages": {
      "Dart": 2481597,
      "C++": 396817,
      "CMake": 299771,
      "Kotlin": 76234,
      "Swift": 67607,
      "Ruby": 52552,
      "HTML": 50091,
      "C": 24897,
      "Shell": 12448,
      "Objective-C": 11888,
      "SCSS": 9957,
      "Java": 9167,
      "JavaScript": 287
    },
    "contributions_by_user": 0,
    "contribution_score": 1707.72,
    "S_code": 3411.44,
    "S_social": 1,
    "S_maint": 0
  },
  {
    "name": "charts",
    "full_name": "stuartmorgan-g/charts",
    "html_url": "https://github.com/stuartmorgan-g/charts",
    "description": null,
    "stars": 1,
    "forks": 0,
    "languages": {
      "Dart": 2680936,
      "Objective-C": 4223,
      "Java": 952,
      "Starlark": 61
    },
    "contributions_by_user": 0,
    "contribution_score": 1313.61,
    "S_code": 2623.21,
    "S_social": 1,
    "S_maint": 0
  },
  {
    "name": "fluttergalleryuwp",
    "full_name": "stuartmorgan-g/fluttergalleryuwp",
    "html_url": "https://github.com/stuartmorgan-g/fluttergalleryuwp",
    "description": "A test for an experimental Windows UWP Flutter embedder",
    "stars": 1,
    "forks": 0,
    "languages": {
      "PowerShell": 4546,
      "C++": 4142,
      "C": 669
    },
    "contributions_by_user": 0,
    "contribution_score": 6.57,
    "S_code": 9.14,
    "S_social": 1,
    "S_maint": 0
  },
  {
    "name": "Dart-Code",
    "full_name": "stuartmorgan-g/Dart-Code",
    "html_url": "https://github.com/stuartmorgan-g/Dart-Code",
    "description": "Dart and Flutter support for Visual Studio Code (VSCode).",
    "stars": 1,
    "forks": 1,
    "languages": {
      "TypeScript": 505977,
      "Dart": 2671,
      "JavaScript": 852
    },
    "contributions_by_user": 0,
    "contribution_score": 254.78,
    "S_code": 497.56,
    "S_social": 3,
    "S_maint": 0
  },
  {
    "name": "flutter-permission-handler",
    "full_name": "stuartmorgan-g/flutter-permission-handler",
    "html_url": "https://github.com/stuartmorgan-g/flutter-permission-handler",
    "description": "Permission plugin for Flutter. This plugin provides a cross-platform (iOS, Android) API to request and check permissions.",
    "stars": 0,
    "forks": 0,
    "languages": {
      "Dart": 292635,
      "C++": 32405,
      "CMake": 18779,
      "Ruby": 7680,
      "Shell": 1555,
      "HTML": 1411
    },
    "contributions_by_user": 0,
    "contribution_score": 173.08,
    "S_code": 346.16,
    "S_social": 0,
    "S_maint": 0
  },
  {
    "name": "cocoon",
    "full_name": "stuartmorgan-g/cocoon",
    "html_url": "https://github.com/stuartmorgan-g/cocoon",
    "description": "Flutter's build coordinator and aggregator",
    "stars": 0,
    "forks": 0,
    "languages": {
      "Dart": 1669922,
      "C++": 24699,
      "Go": 22790,
      "CMake": 14985,
      "Shell": 12435,
      "CSS": 9029,
      "HTML": 7668,
      "Swift": 3974,
      "PowerShell": 3896,
      "Dockerfile": 3572,
      "Batchfile": 1999,
      "C": 1383,
      "Ruby": 1354,
      "JavaScript": 755,
      "Kotlin": 420,
      "Objective-C": 248
    },
    "contributions_by_user": 0,
    "contribution_score": 868.72,
    "S_code": 1737.43,
    "S_social": 0,
    "S_maint": 0
  },
  {
    "name": "win32",
    "full_name": "stuartmorgan-g/win32",
    "html_url": "https://github.com/stuartmorgan-g/win32",
    "description": "Build Win32 apps with Dart!",
    "stars": 0,
    "forks": 0,
    "languages": {
      "Dart": 925941,
      "C++": 103826,
      "CMake": 7751,
      "Shell": 6456,
      "C": 1702,
      "Batchfile": 1019
    },
    "contributions_by_user": 0,
    "contribution_score": 511.08,
    "S_code": 1022.16,
    "S_social": 0,
    "S_maint": 0
  },
  {
    "name": "sdk",
    "full_name": "stuartmorgan-g/sdk",
    "html_url": "https://github.com/stuartmorgan-g/sdk",
    "description": "The Dart SDK, including the VM, dart2js, core libraries, and more.",
    "stars": 0,
    "forks": 0,
    "languages": {
      "Dart": 86891127,
      "C++": 18330886,
      "Python": 1232270,
      "HTML": 678466,
      "Java": 626576,
      "TeX": 271705,
      "C": 170277,
      "JavaScript": 157044,
      "Shell": 154897,
      "CSS": 110202,
      "Batchfile": 49645,
      "GAP": 37402,
      "Makefile": 8113,
      "Assembly": 5209,
      "CMake": 1598,
      "Common Lisp": 234
    },
    "contributions_by_user": 0,
    "contribution_score": 53088.7,
    "S_code": 106177.39,
    "S_social": 0,
    "S_maint": 0
  },
  {
    "name": "plugins",
    "full_name": "stuartmorgan-g/plugins",
    "html_url": "https://github.com/stuartmorgan-g/plugins",
    "description": "Plugins for Flutter, including FlutterFire, maintained by the Flutter team",
    "stars": 0,
    "forks": 1,
    "languages": {
      "Dart": 3285036,
      "Java": 1229074,
      "Objective-C": 575522,
      "C++": 154347,
      "CMake": 92307,
      "Ruby": 67779,
      "Swift": 25861,
      "C": 14137,
      "HTML": 9640,
      "Shell": 9564,
      "Dockerfile": 3172,
      "Kotlin": 131
    },
    "contributions_by_user": 234,
    "contribution_score": 5013.22,
    "S_code": 5338.45,
    "S_social": 2,
    "S_maint": 234
  },
  {
    "name": "web_installers",
    "full_name": "stuartmorgan-g/web_installers",
    "html_url": "https://github.com/stuartmorgan-g/web_installers",
    "description": "Web install scripts for CI for Flutter Web",
    "stars": 0,
    "forks": 0,
    "languages": {
      "Dart": 35965
    },
    "contributions_by_user": 0,
    "contribution_score": 17.56,
    "S_code": 35.12,
    "S_social": 0,
    "S_maint": 0
  },
  {
    "name": "no-response",
    "full_name": "stuartmorgan-g/no-response",
    "html_url": "https://github.com/stuartmorgan-g/no-response",
    "description": "A GitHub Action that closes Issues where the author hasn't responded to a request for more information",
    "stars": 0,
    "forks": 0,
    "languages": {
      "TypeScript": 10811,
      "JavaScript": 235
    },
    "contributions_by_user": 0,
    "contribution_score": 5.39,
    "S_code": 10.79,
    "S_social": 0,
    "S_maint": 0
  },
  {
    "name": "website",
    "full_name": "stuartmorgan-g/website",
    "html_url": "https://github.com/stuartmorgan-g/website",
    "description": "Flutter web site",
    "stars": 0,
    "forks": 0,
    "languages": {
      "Dart": 271576,
      "SCSS": 111916,
      "HTML": 108994,
      "JavaScript": 60630,
      "Shell": 13894,
      "Ruby": 13323,
      "Kotlin": 6173,
      "Dockerfile": 5149,
      "CSS": 2762
    },
    "contributions_by_user": 0,
    "contribution_score": 290.24,
    "S_code": 580.49,
    "S_social": 0,
    "S_maint": 0
  },
  {
    "name": "dart-neats",
    "full_name": "stuartmorgan-g/dart-neats",
    "html_url": "https://github.com/stuartmorgan-g/dart-neats",
    "description": "neat dart packages.",
    "stars": 0,
    "forks": 0,
    "languages": {
      "Dart": 517991,
      "Shell": 6402
    },
    "contributions_by_user": 0,
    "contribution_score": 256.05,
    "S_code": 512.1,
    "S_social": 0,
    "S_maint": 0
  },
  {
    "name": "infra",
    "full_name": "stuartmorgan-g/infra",
    "html_url": "https://github.com/stuartmorgan-g/infra",
    "description": "Contains configuration and tools related to Flutter's build infrastructure.",
    "stars": 0,
    "forks": 0,
    "languages": {
      "Python": 420
    },
    "contributions_by_user": 0,
    "contribution_score": 0.21,
    "S_code": 0.41,
    "S_social": 0,
    "S_maint": 0
  },
  {
    "name": "plugin_tools",
    "full_name": "stuartmorgan-g/plugin_tools",
    "html_url": "https://github.com/stuartmorgan-g/plugin_tools",
    "description": "Productivity utils for hosting multiple plugins within one repository.",
    "stars": 0,
    "forks": 0,
    "languages": {
      "Dart": 149965
    },
    "contributions_by_user": 0,
    "contribution_score": 73.23,
    "S_code": 146.45,
    "S_social": 0,
    "S_maint": 0
  },
  {
    "name": "gallery",
    "full_name": "stuartmorgan-g/gallery",
    "html_url": "https://github.com/stuartmorgan-g/gallery",
    "description": "Flutter Gallery",
    "stars": 0,
    "forks": 0,
    "languages": {
      "Dart": 12291722,
      "Ruby": 3997,
      "HTML": 3122,
      "Swift": 1631,
      "Kotlin": 128,
      "Objective-C": 38
    },
    "contributions_by_user": 1,
    "contribution_score": 6016.17,
    "S_code": 12012.34,
    "S_social": 0,
    "S_maint": 1
  }
]