[
  {
    "name": "ImGuizmo",
    "full_name": "CedricGuillemet/ImGuizmo",
    "html_url": "https://github.com/CedricGuillemet/ImGuizmo",
    "description": "Immediate mode 3D gizmo for scene editing and other controls based on Dear Imgui",
    "stars": 3714,
    "forks": 1025,
    "languages": {
      "C++": 3647420,
      "C": 844886,
      "Makefile": 541,
      "CMake": 515
    },
    "contributions_by_user": 208,
    "contribution_score": 15802.02,
    "S_code": 4388.05,
    "S_social": 5764,
    "S_maint": 208
  },
  {
    "name": "Imogen",
    "full_name": "CedricGuillemet/Imogen",
    "html_url": "https://github.com/CedricGuillemet/Imogen",
    "description": "GPU Texture Generator",
    "stars": 778,
    "forks": 66,
    "languages": {
      "Python": 11545391,
      "C++": 6187090,
      "C": 4567490,
      "GLSL": 141150,
      "CMake": 25010,
      "Objective-C": 18912,
      "Shell": 3786,
      "HTML": 3562,
      "Batchfile": 2366,
      "PowerShell": 1447,
      "CSS": 96
    },
    "contributions_by_user": 657,
    "contribution_score": 19374.52,
    "S_code": 21969.04,
    "S_social": 910,
    "S_maint": 657
  },
  {
    "name": "SDF",
    "full_name": "CedricGuillemet/SDF",
    "html_url": "https://github.com/CedricGuillemet/SDF",
    "description": "Collection of resources (papers, links, discussions, shadertoys,...) related to Signed Distance Field",
    "stars": 749,
    "forks": 30,
    "languages": {},
    "contributions_by_user": 21,
    "contribution_score": 1828.0,
    "S_code": 0.0,
    "S_social": 809,
    "S_maint": 21
  },
  {
    "name": "ImHotKey",
    "full_name": "CedricGuillemet/ImHotKey",
    "html_url": "https://github.com/CedricGuillemet/ImHotKey",
    "description": "Single Header Hotkey editor for dear imgui",
    "stars": 225,
    "forks": 23,
    "languages": {
      "C++": 13720
    },
    "contributions_by_user": 7,
    "contribution_score": 618.7,
    "S_code": 13.4,
    "S_social": 271,
    "S_maint": 7
  },
  {
    "name": "LibGizmo",
    "full_name": "CedricGuillemet/LibGizmo",
    "html_url": "https://github.com/CedricGuillemet/LibGizmo",
    "description": "Gizmo control library for 3D object manipulation (4x4 matrix)",
    "stars": 146,
    "forks": 48,
    "languages": {
      "C++": 117516,
      "C": 61945
    },
    "contributions_by_user": 3,
    "contribution_score": 601.63,
    "S_code": 175.25,
    "S_social": 242,
    "S_maint": 3
  },
  {
    "name": "HexagridRelaxing",
    "full_name": "CedricGuillemet/HexagridRelaxing",
    "html_url": "https://github.com/CedricGuillemet/HexagridRelaxing",
    "description": "hexagonal grid relaxing",
    "stars": 143,
    "forks": 12,
    "languages": {
      "C++": 1321393,
      "C": 663323
    },
    "contributions_by_user": 4,
    "contribution_score": 1343.1,
    "S_code": 1938.2,
    "S_social": 167,
    "S_maint": 4
  },
  {
    "name": "imgInspect",
    "full_name": "CedricGuillemet/imgInspect",
    "html_url": "https://github.com/CedricGuillemet/imgInspect",
    "description": "imgui control to inspect image pixels",
    "stars": 115,
    "forks": 9,
    "languages": {
      "C++": 8952
    },
    "contributions_by_user": 6,
    "contribution_score": 330.37,
    "S_code": 8.74,
    "S_social": 133,
    "S_maint": 6
  },
  {
    "name": "libProfiler",
    "full_name": "CedricGuillemet/libProfiler",
    "html_url": "https://github.com/CedricGuillemet/libProfiler",
    "description": "Profile your c++ code ",
    "stars": 80,
    "forks": 16,
    "languages": {
      "C": 31555,
      "C++": 849
    },
    "contributions_by_user": 6,
    "contribution_score": 299.82,
    "S_code": 31.64,
    "S_social": 112,
    "S_maint": 6
  },
  {
    "name": "bam",
    "full_name": "CedricGuillemet/bam",
    "html_url": "https://github.com/CedricGuillemet/bam",
    "description": "Framework for multiplatform prototypes",
    "stars": 42,
    "forks": 6,
    "languages": {
      "Shell": 40707,
      "C": 37920,
      "C++": 10600,
      "CMake": 9737,
      "GLSL": 6784,
      "HTML": 3553,
      "RenderScript": 302,
      "SuperCollider": 248
    },
    "contributions_by_user": 26,
    "contribution_score": 421.64,
    "S_code": 107.28,
    "S_social": 54,
    "S_maint": 26
  },
  {
    "name": "GPT-Toolbox",
    "full_name": "CedricGuillemet/GPT-Toolbox",
    "html_url": "https://github.com/CedricGuillemet/GPT-Toolbox",
    "description": "GPT extension for VSCode",
    "stars": 29,
    "forks": 2,
    "languages": {
      "TypeScript": 3450,
      "JavaScript": 507
    },
    "contributions_by_user": 1,
    "contribution_score": 77.93,
    "S_code": 3.86,
    "S_social": 33,
    "S_maint": 1
  },
  {
    "name": "BlenderLiveUpdate",
    "full_name": "CedricGuillemet/BlenderLiveUpdate",
    "html_url": "https://github.com/CedricGuillemet/BlenderLiveUpdate",
    "description": "Live HTTP/GLTF2 link between Blender and any tool that can stream assets like Babylon.js Playground",
    "stars": 27,
    "forks": 2,
    "languages": {
      "Python": 2050
    },
    "contributions_by_user": 5,
    "contribution_score": 113.0,
    "S_code": 2.0,
    "S_social": 31,
    "S_maint": 5
  },
  {
    "name": "NeRF",
    "full_name": "CedricGuillemet/NeRF",
    "html_url": "https://github.com/CedricGuillemet/NeRF",
    "description": "Collection of resources around NeRF",
    "stars": 25,
    "forks": 1,
    "languages": {},
    "contributions_by_user": 5,
    "contribution_score": 104.0,
    "S_code": 0.0,
    "S_social": 27,
    "S_maint": 5
  },
  {
    "name": "Shatter",
    "full_name": "CedricGuillemet/Shatter",
    "html_url": "https://github.com/CedricGuillemet/Shatter",
    "description": "Mesh shatter library",
    "stars": 24,
    "forks": 2,
    "languages": {
      "C++": 21055
    },
    "contributions_by_user": 2,
    "contribution_score": 86.28,
    "S_code": 20.56,
    "S_social": 28,
    "S_maint": 2
  },
  {
    "name": "AndroidAppViewer",
    "full_name": "CedricGuillemet/AndroidAppViewer",
    "html_url": "https://github.com/CedricGuillemet/AndroidAppViewer",
    "description": "Android GLES3 stub",
    "stars": 17,
    "forks": 3,
    "languages": {
      "C": 56100,
      "Java": 30168,
      "C++": 11558,
      "CMake": 1978
    },
    "contributions_by_user": 8,
    "contribution_score": 174.73,
    "S_code": 97.46,
    "S_social": 23,
    "S_maint": 8
  },
  {
    "name": "Flooid",
    "full_name": "CedricGuillemet/Flooid",
    "html_url": "https://github.com/CedricGuillemet/Flooid",
    "description": "Fluid simulation",
    "stars": 16,
    "forks": 0,
    "languages": {
      "C++": 108291,
      "Shell": 47931,
      "C#": 22029,
      "GLSL": 21765,
      "CMake": 10047,
      "C": 7628,
      "HTML": 3553,
      "RenderScript": 302,
      "SuperCollider": 280
    },
    "contributions_by_user": 140,
    "contribution_score": 1540.31,
    "S_code": 216.63,
    "S_social": 16,
    "S_maint": 140
  },
  {
    "name": "Kapsul3D",
    "full_name": "CedricGuillemet/Kapsul3D",
    "html_url": "https://github.com/CedricGuillemet/Kapsul3D",
    "description": "Kapsul 3D modeler 1999-2002",
    "stars": 14,
    "forks": 2,
    "languages": {
      "C++": 8320471,
      "C": 4025999,
      "Makefile": 285224,
      "HTML": 48213,
      "Objective-C": 46229,
      "Inno Setup": 26794,
      "Scala": 19296,
      "Batchfile": 801
    },
    "contributions_by_user": 2,
    "contribution_score": 6292.83,
    "S_code": 12473.66,
    "S_social": 18,
    "S_maint": 2
  },
  {
    "name": "WaveFunctionCollapse",
    "full_name": "CedricGuillemet/WaveFunctionCollapse",
    "html_url": "https://github.com/CedricGuillemet/WaveFunctionCollapse",
    "description": "Simple C++ implementation of Wave Function Collapse",
    "stars": 9,
    "forks": 3,
    "languages": {
      "C++": 8092,
      "C": 616
    },
    "contributions_by_user": 2,
    "contribution_score": 54.25,
    "S_code": 8.5,
    "S_social": 15,
    "S_maint": 2
  },
  {
    "name": "babylonnative_flutter",
    "full_name": "CedricGuillemet/babylonnative_flutter",
    "html_url": "https://github.com/CedricGuillemet/babylonnative_flutter",
    "description": "BabylonNative for Flutter",
    "stars": 8,
    "forks": 3,
    "languages": {
      "C++": 37599,
      "CMake": 26082,
      "Java": 8840,
      "Dart": 8055,
      "Objective-C": 4155,
      "Ruby": 2941,
      "C": 2649,
      "Swift": 1526,
      "Shell": 1086
    },
    "contributions_by_user": 43,
    "contribution_score": 503.38,
    "S_code": 90.75,
    "S_social": 14,
    "S_maint": 43
  },
  {
    "name": "Immath",
    "full_name": "CedricGuillemet/Immath",
    "html_url": "https://github.com/CedricGuillemet/Immath",
    "description": "Vector/Matrix/Math library",
    "stars": 7,
    "forks": 0,
    "languages": {
      "C++": 74157,
      "CMake": 133
    },
    "contributions_by_user": 7,
    "contribution_score": 120.27,
    "S_code": 72.55,
    "S_social": 7,
    "S_maint": 7
  },
  {
    "name": "GLSL-PathTracer",
    "full_name": "CedricGuillemet/GLSL-PathTracer",
    "html_url": "https://github.com/CedricGuillemet/GLSL-PathTracer",
    "description": "A GLSL Path Tracer",
    "stars": 6,
    "forks": 2,
    "languages": {
      "C++": 211448,
      "GLSL": 60147
    },
    "contributions_by_user": 0,
    "contribution_score": 152.61,
    "S_code": 265.23,
    "S_social": 10,
    "S_maint": 0
  },
  {
    "name": "bgfx",
    "full_name": "CedricGuillemet/bgfx",
    "html_url": "https://github.com/CedricGuillemet/bgfx",
    "description": "Cross-platform, graphics API agnostic, \"Bring Your Own Engine/Framework\" style rendering library.",
    "stars": 4,
    "forks": 1,
    "languages": {
      "C++": 2472191,
      "C": 1195090,
      "Lua": 264327,
      "D": 231093,
      "Objective-C++": 166172,
      "C#": 165643,
      "HyPhy": 152086,
      "Shell": 45632,
      "Makefile": 29907,
      "Objective-C": 28802,
      "SuperCollider": 6870,
      "Scala": 4632
    },
    "contributions_by_user": 14,
    "contribution_score": 2477.41,
    "S_code": 4650.83,
    "S_social": 6,
    "S_maint": 14
  },
  {
    "name": "arcana.cpp",
    "full_name": "CedricGuillemet/arcana.cpp",
    "html_url": "https://github.com/CedricGuillemet/arcana.cpp",
    "description": "Arcana.cpp is a collection of helpers and utility code for low overhead, cross platform C++ implementation of task-based asynchrony.",
    "stars": 4,
    "forks": 1,
    "languages": {
      "C++": 340828,
      "C": 531
    },
    "contributions_by_user": 0,
    "contribution_score": 178.68,
    "S_code": 333.36,
    "S_social": 6,
    "S_maint": 0
  },
  {
    "name": "mp4-h264",
    "full_name": "CedricGuillemet/mp4-h264",
    "html_url": "https://github.com/CedricGuillemet/mp4-h264",
    "description": "mp4 h264 encoder decoder",
    "stars": 4,
    "forks": 1,
    "languages": {},
    "contributions_by_user": 2,
    "contribution_score": 32.0,
    "S_code": 0.0,
    "S_social": 6,
    "S_maint": 2
  },
  {
    "name": "imgui_markdown",
    "full_name": "CedricGuillemet/imgui_markdown",
    "html_url": "https://github.com/CedricGuillemet/imgui_markdown",
    "description": "Markdown for Dear ImGui",
    "stars": 4,
    "forks": 1,
    "languages": {
      "C++": 22601
    },
    "contributions_by_user": 0,
    "contribution_score": 23.04,
    "S_code": 22.07,
    "S_social": 6,
    "S_maint": 0
  },
  {
    "name": "dump",
    "full_name": "CedricGuillemet/dump",
    "html_url": "https://github.com/CedricGuillemet/dump",
    "description": "Dump files/Tests. Nothing interesting here",
    "stars": 3,
    "forks": 2,
    "languages": {
      "JavaScript": 470406,
      "C++": 6551
    },
    "contributions_by_user": 166,
    "contribution_score": 1906.89,
    "S_code": 465.78,
    "S_social": 7,
    "S_maint": 166
  },
  {
    "name": "cedricguillemet.github.io",
    "full_name": "CedricGuillemet/cedricguillemet.github.io",
    "html_url": "https://github.com/CedricGuillemet/cedricguillemet.github.io",
    "description": "Home",
    "stars": 3,
    "forks": 0,
    "languages": {
      "HTML": 14984872,
      "JavaScript": 1387857
    },
    "contributions_by_user": 63,
    "contribution_score": 8630.5,
    "S_code": 15988.99,
    "S_social": 3,
    "S_maint": 63
  },
  {
    "name": "Imog3n",
    "full_name": "CedricGuillemet/Imog3n",
    "html_url": "https://github.com/CedricGuillemet/Imog3n",
    "description": null,
    "stars": 3,
    "forks": 0,
    "languages": {
      "C": 1426786,
      "C++": 76166,
      "Shell": 40707,
      "GLSL": 20630,
      "CMake": 8924,
      "HTML": 3556,
      "SuperCollider": 248
    },
    "contributions_by_user": 22,
    "contribution_score": 996.03,
    "S_code": 1540.06,
    "S_social": 3,
    "S_maint": 22
  },
  {
    "name": "linky",
    "full_name": "CedricGuillemet/linky",
    "html_url": "https://github.com/CedricGuillemet/linky",
    "description": null,
    "stars": 2,
    "forks": 0,
    "languages": {
      "Python": 20875,
      "Shell": 171
    },
    "contributions_by_user": 34,
    "contribution_score": 354.28,
    "S_code": 20.55,
    "S_social": 2,
    "S_maint": 34
  },
  {
    "name": "gli",
    "full_name": "CedricGuillemet/gli",
    "html_url": "https://github.com/CedricGuillemet/gli",
    "description": "OpenGL Image (GLI)",
    "stars": 2,
    "forks": 0,
    "languages": {
      "C++": 1382757,
      "CMake": 27078
    },
    "contributions_by_user": 0,
    "contribution_score": 692.4,
    "S_code": 1376.79,
    "S_social": 2,
    "S_maint": 0
  },
  {
    "name": "theRush",
    "full_name": "CedricGuillemet/theRush",
    "html_url": "https://github.com/CedricGuillemet/theRush",
    "description": "The rush ",
    "stars": 2,
    "forks": 1,
    "languages": {
      "C++": 11802893,
      "C": 3719338,
      "CMake": 75911,
      "Objective-C": 75192,
      "GLSL": 55620,
      "HLSL": 39754,
      "Makefile": 36605,
      "Inno Setup": 25121
    },
    "contributions_by_user": 1,
    "contribution_score": 7747.7,
    "S_code": 15459.41,
    "S_social": 4,
    "S_maint": 1
  },
  {
    "name": "Babylon.js",
    "full_name": "CedricGuillemet/Babylon.js",
    "html_url": "https://github.com/CedricGuillemet/Babylon.js",
    "description": "Babylon.js is a powerful, beautiful, simple, and open game and rendering engine packed into a friendly JavaScript framework.",
    "stars": 1,
    "forks": 0,
    "languages": {
      "TypeScript": 24994201,
      "HLSL": 1671572,
      "JavaScript": 1300415,
      "SCSS": 438203,
      "Roff": 276786,
      "HTML": 126097,
      "FLUX": 12321,
      "Batchfile": 12
    },
    "contributions_by_user": 546,
    "contribution_score": 19534.07,
    "S_code": 28144.15,
    "S_social": 1,
    "S_maint": 546
  },
  {
    "name": "CedricGuillemet",
    "full_name": "CedricGuillemet/CedricGuillemet",
    "html_url": "https://github.com/CedricGuillemet/CedricGuillemet",
    "description": "Config files for my GitHub profile.",
    "stars": 1,
    "forks": 1,
    "languages": {},
    "contributions_by_user": 8,
    "contribution_score": 86.0,
    "S_code": 0.0,
    "S_social": 3,
    "S_maint": 8
  },
  {
    "name": "ez-tree",
    "full_name": "CedricGuillemet/ez-tree",
    "html_url": "https://github.com/CedricGuillemet/ez-tree",
    "description": "Procedural tree generator written with JavaScript and Babylon.js",
    "stars": 1,
    "forks": 0,
    "languages": {
      "JavaScript": 78632,
      "CSS": 4703,
      "HTML": 4345,
      "GLSL": 1302,
      "Dockerfile": 567
    },
    "contributions_by_user": 0,
    "contribution_score": 45.73,
    "S_code": 87.45,
    "S_social": 1,
    "S_maint": 0
  },
  {
    "name": "BrightDreamer",
    "full_name": "CedricGuillemet/BrightDreamer",
    "html_url": "https://github.com/CedricGuillemet/BrightDreamer",
    "description": "BrightDreamer: Generic 3D Gaussian Generative Framework for Fast Text-to-3D Synthesis",
    "stars": 1,
    "forks": 0,
    "languages": {
      "Python": 872249,
      "Cuda": 102195,
      "C++": 33341,
      "HTML": 5629,
      "Shell": 1796
    },
    "contributions_by_user": 0,
    "contribution_score": 497.71,
    "S_code": 991.42,
    "S_social": 1,
    "S_maint": 0
  },
  {
    "name": "shmup",
    "full_name": "CedricGuillemet/shmup",
    "html_url": "https://github.com/CedricGuillemet/shmup",
    "description": "shmup",
    "stars": 1,
    "forks": 0,
    "languages": {
      "C++": 4553729,
      "C": 3465007,
      "CMake": 20951,
      "Objective-C": 9352
    },
    "contributions_by_user": 44,
    "contribution_score": 4372.19,
    "S_code": 7860.39,
    "S_social": 1,
    "S_maint": 44
  },
  {
    "name": "VorteGrid",
    "full_name": "CedricGuillemet/VorteGrid",
    "html_url": "https://github.com/CedricGuillemet/VorteGrid",
    "description": "VorteGrid: Interactive Fluid Simulation for Games and Movies",
    "stars": 1,
    "forks": 0,
    "languages": {},
    "contributions_by_user": 0,
    "contribution_score": 2.0,
    "S_code": 0.0,
    "S_social": 1,
    "S_maint": 0
  },
  {
    "name": "gemoni",
    "full_name": "CedricGuillemet/gemoni",
    "html_url": "https://github.com/CedricGuillemet/gemoni",
    "description": "Imogen 2",
    "stars": 1,
    "forks": 1,
    "languages": {
      "C++": 2114704,
      "C": 604471,
      "Objective-C++": 31340,
      "CMake": 5096,
      "Objective-C": 3171
    },
    "contributions_by_user": 36,
    "contribution_score": 1713.06,
    "S_code": 2694.12,
    "S_social": 3,
    "S_maint": 36
  },
  {
    "name": "bx",
    "full_name": "CedricGuillemet/bx",
    "html_url": "https://github.com/CedricGuillemet/bx",
    "description": "Base library used across multiple projects",
    "stars": 1,
    "forks": 0,
    "languages": {
      "C++": 821218,
      "C": 377204,
      "Lua": 44275,
      "Makefile": 8153
    },
    "contributions_by_user": 0,
    "contribution_score": 612.77,
    "S_code": 1221.53,
    "S_social": 1,
    "S_maint": 0
  },
  {
    "name": "ammo.js",
    "full_name": "CedricGuillemet/ammo.js",
    "html_url": "https://github.com/CedricGuillemet/ammo.js",
    "description": "Direct port of the Bullet physics engine to JavaScript using Emscripten",
    "stars": 1,
    "forks": 0,
    "languages": {
      "C++": 13194574,
      "C": 3132159,
      "RPC": 1557205,
      "CMake": 192802,
      "M4": 151447,
      "Cuda": 94563,
      "Objective-C": 74993,
      "JavaScript": 46705,
      "Makefile": 44881,
      "Python": 17826,
      "HLSL": 12613,
      "TeX": 12612,
      "Lua": 12245,
      "Shell": 10752,
      "Objective-C++": 8171,
      "HTML": 1223,
      "Batchfile": 636,
      "Rich Text Format": 432,
      "GLSL": 281
    },
    "contributions_by_user": 0,
    "contribution_score": 9067.49,
    "S_code": 18130.98,
    "S_social": 1,
    "S_maint": 0
  },
  {
    "name": "remoteimgui",
    "full_name": "CedricGuillemet/remoteimgui",
    "html_url": "https://github.com/CedricGuillemet/remoteimgui",
    "description": "Remote ImGui for https://github.com/ocornut/imgui",
    "stars": 1,
    "forks": 1,
    "languages": {
      "C": 332250,
      "JavaScript": 282629,
      "C++": 82612,
      "Objective-C++": 20667,
      "Objective-C": 5684,
      "CSS": 2239,
      "HTML": 2224
    },
    "contributions_by_user": 2,
    "contribution_score": 381.62,
    "S_code": 711.24,
    "S_social": 3,
    "S_maint": 2
  },
  {
    "name": "imgui",
    "full_name": "CedricGuillemet/imgui",
    "html_url": "https://github.com/CedricGuillemet/imgui",
    "description": "Bloat-free Immediate Mode Graphical User interface for C++ with minimal dependencies",
    "stars": 1,
    "forks": 2,
    "languages": {
      "C++": 723801,
      "C": 627320,
      "Makefile": 1993
    },
    "contributions_by_user": 0,
    "contribution_score": 670.7,
    "S_code": 1321.4,
    "S_social": 5,
    "S_maint": 0
  },
  {
    "name": "Inspirations",
    "full_name": "CedricGuillemet/Inspirations",
    "html_url": "https://github.com/CedricGuillemet/Inspirations",
    "description": "Bunch of things for inspiration",
    "stars": 0,
    "forks": 0,
    "languages": {},
    "contributions_by_user": 47,
    "contribution_score": 470.0,
    "S_code": 0.0,
    "S_social": 0,
    "S_maint": 47
  },
  {
    "name": "Documentation",
    "full_name": "CedricGuillemet/Documentation",
    "html_url": "https://github.com/CedricGuillemet/Documentation",
    "description": "Babylon.js's documentation website",
    "stars": 0,
    "forks": 0,
    "languages": {
      "TypeScript": 195927,
      "SCSS": 122428,
      "HTML": 32378,
      "Sass": 1895,
      "JavaScript": 572
    },
    "contributions_by_user": 16,
    "contribution_score": 332.46,
    "S_code": 344.92,
    "S_social": 0,
    "S_maint": 16
  },
  {
    "name": "BabylonNative",
    "full_name": "CedricGuillemet/BabylonNative",
    "html_url": "https://github.com/CedricGuillemet/BabylonNative",
    "description": "Build cross-platform native applications with the power of the Babylon.js JavaScript framework",
    "stars": 0,
    "forks": 0,
    "languages": {
      "C++": 828735,
      "Objective-C++": 74466,
      "CMake": 56256,
      "JavaScript": 49359,
      "Java": 10073,
      "Swift": 7480,
      "Objective-C": 1443,
      "C": 1063
    },
    "contributions_by_user": 490,
    "contribution_score": 5402.38,
    "S_code": 1004.76,
    "S_social": 0,
    "S_maint": 490
  },
  {
    "name": "JsRuntimeHost",
    "full_name": "CedricGuillemet/JsRuntimeHost",
    "html_url": "https://github.com/CedricGuillemet/JsRuntimeHost",
    "description": "The JsRuntimeHost is a library that provides cross-platform C++ JavaScript hosting for any JavaScript engines with Node-API support such as Chakra, V8, or JavaScriptCore.",
    "stars": 0,
    "forks": 0,
    "languages": {
      "C++": 817127,
      "C": 29682,
      "CMake": 29472,
      "JavaScript": 21551,
      "Java": 2379,
      "Objective-C++": 1598
    },
    "contributions_by_user": 10,
    "contribution_score": 540.34,
    "S_code": 880.67,
    "S_social": 0,
    "S_maint": 10
  },
  {
    "name": "twgsl",
    "full_name": "CedricGuillemet/twgsl",
    "html_url": "https://github.com/CedricGuillemet/twgsl",
    "description": null,
    "stars": 0,
    "forks": 0,
    "languages": {
      "C++": 3017,
      "JavaScript": 2387,
      "CMake": 1123
    },
    "contributions_by_user": 42,
    "contribution_score": 423.19,
    "S_code": 6.37,
    "S_social": 0,
    "S_maint": 42
  },
  {
    "name": "BabylonReactNative-1",
    "full_name": "CedricGuillemet/BabylonReactNative-1",
    "html_url": "https://github.com/CedricGuillemet/BabylonReactNative-1",
    "description": "Build React Native applications with the power of Babylon Native",
    "stars": 0,
    "forks": 1,
    "languages": {
      "C++": 134846,
      "Java": 93192,
      "JavaScript": 73463,
      "TypeScript": 39964,
      "Objective-C": 33302,
      "Objective-C++": 24466,
      "CMake": 17832,
      "Ruby": 15312,
      "Starlark": 7446,
      "PowerShell": 6669,
      "Makefile": 3019,
      "C": 2354,
      "Batchfile": 660
    },
    "contributions_by_user": 75,
    "contribution_score": 974.96,
    "S_code": 441.92,
    "S_social": 2,
    "S_maint": 75
  },
  {
    "name": "Tool1",
    "full_name": "CedricGuillemet/Tool1",
    "html_url": "https://github.com/CedricGuillemet/Tool1",
    "description": "I don't know what I'm doing.",
    "stars": 0,
    "forks": 0,
    "languages": {
      "C++": 4457858,
      "C": 752120,
      "Objective-C++": 42169,
      "CMake": 4265,
      "Objective-C": 2279,
      "Assembly": 821
    },
    "contributions_by_user": 9,
    "contribution_score": 2658.12,
    "S_code": 5136.24,
    "S_social": 0,
    "S_maint": 9
  },
  {
    "name": "Assets",
    "full_name": "CedricGuillemet/Assets",
    "html_url": "https://github.com/CedricGuillemet/Assets",
    "description": "A place for public domain digital assets to use.",
    "stars": 0,
    "forks": 0,
    "languages": {
      "JavaScript": 10930748,
      "Mathematica": 3306541,
      "Roff": 753234,
      "HTML": 2639
    },
    "contributions_by_user": 0,
    "contribution_score": 7320.88,
    "S_code": 14641.76,
    "S_social": 0,
    "S_maint": 0
  },
  {
    "name": "BabylonReactNative",
    "full_name": "CedricGuillemet/BabylonReactNative",
    "html_url": "https://github.com/CedricGuillemet/BabylonReactNative",
    "description": "Babylon Native integration with React Native",
    "stars": 0,
    "forks": 0,
    "languages": {
      "Java": 5314,
      "Objective-C": 4669,
      "TypeScript": 3623,
      "Ruby": 3606,
      "JavaScript": 3407,
      "CMake": 3303,
      "Starlark": 602,
      "C++": 298
    },
    "contributions_by_user": 0,
    "contribution_score": 12.12,
    "S_code": 24.24,
    "S_social": 0,
    "S_maint": 0
  },
  {
    "name": "gradio",
    "full_name": "CedricGuillemet/gradio",
    "html_url": "https://github.com/CedricGuillemet/gradio",
    "description": "Build and share delightful machine learning apps, all in Python. 🌟 Star to support our work!",
    "stars": 0,
    "forks": 0,
    "languages": {
      "Python": 2836996,
      "Svelte": 930624,
      "TypeScript": 850420,
      "JavaScript": 47776,
      "Jupyter Notebook": 32113,
      "CSS": 30527,
      "HTML": 21150,
      "Shell": 6425,
      "Roff": 5780,
      "MDX": 1670
    },
    "contributions_by_user": 0,
    "contribution_score": 2325.92,
    "S_code": 4651.84,
    "S_social": 0,
    "S_maint": 0
  },
  {
    "name": "bgfx.cmake",
    "full_name": "CedricGuillemet/bgfx.cmake",
    "html_url": "https://github.com/CedricGuillemet/bgfx.cmake",
    "description": "Independently maintained CMake build scripts for bgfx. Released under public domain.",
    "stars": 0,
    "forks": 0,
    "languages": {
      "CMake": 72479,
      "Python": 12822
    },
    "contributions_by_user": 0,
    "contribution_score": 41.65,
    "S_code": 83.3,
    "S_social": 0,
    "S_maint": 0
  },
  {
    "name": "bimg",
    "full_name": "CedricGuillemet/bimg",
    "html_url": "https://github.com/CedricGuillemet/bimg",
    "description": "Image library.",
    "stars": 0,
    "forks": 1,
    "languages": {
      "C++": 327328,
      "Makefile": 14788,
      "Lua": 5357
    },
    "contributions_by_user": 0,
    "contribution_score": 173.66,
    "S_code": 339.33,
    "S_social": 2,
    "S_maint": 0
  },
  {
    "name": "Extensions",
    "full_name": "CedricGuillemet/Extensions",
    "html_url": "https://github.com/CedricGuillemet/Extensions",
    "description": "Extensions for Babylon.js",
    "stars": 0,
    "forks": 0,
    "languages": {
      "JavaScript": 21252742,
      "TypeScript": 1630475,
      "HTML": 179841,
      "C#": 63962,
      "C++": 51216,
      "HLSL": 16633,
      "CSS": 8538,
      "CMake": 7046,
      "Java": 1422
    },
    "contributions_by_user": 18,
    "contribution_score": 11513.92,
    "S_code": 22667.85,
    "S_social": 0,
    "S_maint": 18
  },
  {
    "name": "tinyusdz",
    "full_name": "CedricGuillemet/tinyusdz",
    "html_url": "https://github.com/CedricGuillemet/tinyusdz",
    "description": "Tiny, dependency-free USDZ/USDA/USDC library written in C++14",
    "stars": 0,
    "forks": 0,
    "languages": {
      "C++": 6530278,
      "C": 797483,
      "Python": 361701,
      "JavaScript": 207451,
      "CMake": 184371,
      "Metal": 147711,
      "GLSL": 133858,
      "HLSL": 115329,
      "Objective-C": 114487,
      "Objective-C++": 41551,
      "NASL": 37596,
      "Cuda": 15404,
      "Shell": 15296,
      "Kotlin": 6295,
      "Meson": 5164,
      "Makefile": 3140,
      "Batchfile": 2730,
      "TypeScript": 1834,
      "DTrace": 1008,
      "HTML": 774,
      "PHP": 716,
      "Dockerfile": 212
    },
    "contributions_by_user": 3,
    "contribution_score": 4289.96,
    "S_code": 8519.91,
    "S_social": 0,
    "S_maint": 3
  },
  {
    "name": "Cannon",
    "full_name": "CedricGuillemet/Cannon",
    "html_url": "https://github.com/CedricGuillemet/Cannon",
    "description": null,
    "stars": 0,
    "forks": 0,
    "languages": {
      "Python": 5987
    },
    "contributions_by_user": 6,
    "contribution_score": 62.92,
    "S_code": 5.85,
    "S_social": 0,
    "S_maint": 6
  },
  {
    "name": "SPIRV-Cross",
    "full_name": "CedricGuillemet/SPIRV-Cross",
    "html_url": "https://github.com/CedricGuillemet/SPIRV-Cross",
    "description": "SPIRV-Cross is a practical tool and library for performing reflection on SPIR-V and disassembling SPIR-V back to high level languages.",
    "stars": 0,
    "forks": 0,
    "languages": {
      "GLSL": 5260616,
      "C++": 3327764,
      "JavaScript": 287403,
      "C": 199749,
      "Python": 41146,
      "CMake": 26771,
      "Shell": 4117,
      "Swift": 2743,
      "Assembly": 2388,
      "Makefile": 908
    },
    "contributions_by_user": 0,
    "contribution_score": 4469.53,
    "S_code": 8939.07,
    "S_social": 0,
    "S_maint": 0
  },
  {
    "name": "txt2mesh",
    "full_name": "CedricGuillemet/txt2mesh",
    "html_url": "https://github.com/CedricGuillemet/txt2mesh",
    "description": null,
    "stars": 0,
    "forks": 0,
    "languages": {
      "TypeScript": 33228,
      "JavaScript": 12487,
      "GLSL": 1038,
      "HTML": 644
    },
    "contributions_by_user": 2,
    "contribution_score": 43.14,
    "S_code": 46.29,
    "S_social": 0,
    "S_maint": 2
  },
  {
    "name": "Website",
    "full_name": "CedricGuillemet/Website",
    "html_url": "https://github.com/CedricGuillemet/Website",
    "description": "Main babylon.js website",
    "stars": 0,
    "forks": 0,
    "languages": {
      "JavaScript": 46774176,
      "HTML": 1461323,
      "CSS": 263213,
      "TypeScript": 191516,
      "Roff": 68318,
      "HLSL": 43114,
      "GLSL": 1399,
      "C#": 1349,
      "ASP.NET": 96
    },
    "contributions_by_user": 0,
    "contribution_score": 23830.32,
    "S_code": 47660.65,
    "S_social": 0,
    "S_maint": 0
  },
  {
    "name": "v8-android-buildscripts",
    "full_name": "CedricGuillemet/v8-android-buildscripts",
    "html_url": "https://github.com/CedricGuillemet/v8-android-buildscripts",
    "description": "V8 build scripts for React Native Android",
    "stars": 0,
    "forks": 0,
    "languages": {
      "Shell": 17875,
      "Python": 9136,
      "C++": 4863,
      "Ruby": 636
    },
    "contributions_by_user": 0,
    "contribution_score": 15.87,
    "S_code": 31.75,
    "S_social": 0,
    "S_maint": 0
  },
  {
    "name": "glslang",
    "full_name": "CedricGuillemet/glslang",
    "html_url": "https://github.com/CedricGuillemet/glslang",
    "description": "Khronos-reference front end for GLSL/ESSL, partial front end for HLSL, and a SPIR-V generator.",
    "stars": 0,
    "forks": 0,
    "languages": {
      "C++": 5606405,
      "GLSL": 1197958,
      "M4": 175219,
      "Yacc": 173847,
      "JavaScript": 169088,
      "C": 98372,
      "CMake": 63690,
      "Shell": 51352,
      "Python": 19408,
      "Makefile": 10221,
      "HLSL": 2178,
      "Starlark": 1043
    },
    "contributions_by_user": 0,
    "contribution_score": 3695.69,
    "S_code": 7391.39,
    "S_social": 0,
    "S_maint": 0
  },
  {
    "name": "BabylonReactNativeSample",
    "full_name": "CedricGuillemet/BabylonReactNativeSample",
    "html_url": "https://github.com/CedricGuillemet/BabylonReactNativeSample",
    "description": null,
    "stars": 0,
    "forks": 0,
    "languages": {
      "Java": 6285,
      "Objective-C": 4544,
      "TypeScript": 3130,
      "JavaScript": 1161,
      "Ruby": 1049,
      "Starlark": 602
    },
    "contributions_by_user": 0,
    "contribution_score": 8.19,
    "S_code": 16.38,
    "S_social": 0,
    "S_maint": 0
  },
  {
    "name": "UrlLib",
    "full_name": "CedricGuillemet/UrlLib",
    "html_url": "https://github.com/CedricGuillemet/UrlLib",
    "description": "UrlLib is a cross-platform C++ library that utilizes platform-specific implementations for URL-related functionality",
    "stars": 0,
    "forks": 0,
    "languages": {
      "C++": 40899,
      "Objective-C++": 7108,
      "Objective-C": 3805,
      "CMake": 2499
    },
    "contributions_by_user": 2,
    "contribution_score": 46.52,
    "S_code": 53.04,
    "S_social": 0,
    "S_maint": 2
  },
  {
    "name": "BabylonReactNativeProtocolCheck",
    "full_name": "CedricGuillemet/BabylonReactNativeProtocolCheck",
    "html_url": "https://github.com/CedricGuillemet/BabylonReactNativeProtocolCheck",
    "description": "Check compatibility of Babylon.js/BabylonNative and BabylonReactNative",
    "stars": 0,
    "forks": 0,
    "languages": {
      "JavaScript": 5711
    },
    "contributions_by_user": 1,
    "contribution_score": 12.79,
    "S_code": 5.58,
    "S_social": 0,
    "S_maint": 1
  },
  {
    "name": "GARegex",
    "full_name": "CedricGuillemet/GARegex",
    "html_url": "https://github.com/CedricGuillemet/GARegex",
    "description": "GitHub Actions With regex",
    "stars": 0,
    "forks": 0,
    "languages": {
      "C++": 121,
      "C": 62
    },
    "contributions_by_user": 38,
    "contribution_score": 380.09,
    "S_code": 0.18,
    "S_social": 0,
    "S_maint": 38
  },
  {
    "name": "PhysSample",
    "full_name": "CedricGuillemet/PhysSample",
    "html_url": "https://github.com/CedricGuillemet/PhysSample",
    "description": null,
    "stars": 0,
    "forks": 0,
    "languages": {
      "JavaScript": 2851,
      "TypeScript": 2630
    },
    "contributions_by_user": 3,
    "contribution_score": 32.68,
    "S_code": 5.35,
    "S_social": 0,
    "S_maint": 3
  },
  {
    "name": "Bandai-Namco-Research-Motiondataset",
    "full_name": "CedricGuillemet/Bandai-Namco-Research-Motiondataset",
    "html_url": "https://github.com/CedricGuillemet/Bandai-Namco-Research-Motiondataset",
    "description": "This repository provides motion datasets collected by Bandai Namco Research Inc",
    "stars": 0,
    "forks": 0,
    "languages": {
      "Python": 4223
    },
    "contributions_by_user": 0,
    "contribution_score": 2.06,
    "S_code": 4.12,
    "S_social": 0,
    "S_maint": 0
  },
  {
    "name": "Motion-Matching",
    "full_name": "CedricGuillemet/Motion-Matching",
    "html_url": "https://github.com/CedricGuillemet/Motion-Matching",
    "description": "Source code for the article \"Code vs Data Driven Displacement\"",
    "stars": 0,
    "forks": 0,
    "languages": {
      "C": 129075,
      "Python": 29013,
      "C++": 5483,
      "GLSL": 783
    },
    "contributions_by_user": 0,
    "contribution_score": 80.25,
    "S_code": 160.5,
    "S_social": 0,
    "S_maint": 0
  },
  {
    "name": "probable-barnacle",
    "full_name": "CedricGuillemet/probable-barnacle",
    "html_url": "https://github.com/CedricGuillemet/probable-barnacle",
    "description": "Prototype for Babylon Proving Ground",
    "stars": 0,
    "forks": 0,
    "languages": {
      "JavaScript": 2541,
      "TypeScript": 2258
    },
    "contributions_by_user": 0,
    "contribution_score": 2.34,
    "S_code": 4.69,
    "S_social": 0,
    "S_maint": 0
  },
  {
    "name": "glTF-SDK",
    "full_name": "CedricGuillemet/glTF-SDK",
    "html_url": "https://github.com/CedricGuillemet/glTF-SDK",
    "description": "glTF-SDK is a C++ Software Development Kit for glTF (GL Transmission Format -https://github.com/KhronosGroup/glTF).",
    "stars": 0,
    "forks": 0,
    "languages": {
      "C++": 812282,
      "PowerShell": 154396,
      "CMake": 38779,
      "C": 764,
      "Shell": 158
    },
    "contributions_by_user": 0,
    "contribution_score": 491.4,
    "S_code": 982.79,
    "S_social": 0,
    "S_maint": 0
  },
  {
    "name": "ragdoll.js",
    "full_name": "CedricGuillemet/ragdoll.js",
    "html_url": "https://github.com/CedricGuillemet/ragdoll.js",
    "description": "Ragdolls on the browser",
    "stars": 0,
    "forks": 0,
    "languages": {
      "JavaScript": 14072,
      "HTML": 9786
    },
    "contributions_by_user": 0,
    "contribution_score": 11.65,
    "S_code": 23.3,
    "S_social": 0,
    "S_maint": 0
  },
  {
    "name": "ubisoft-laforge-animation-dataset",
    "full_name": "CedricGuillemet/ubisoft-laforge-animation-dataset",
    "html_url": "https://github.com/CedricGuillemet/ubisoft-laforge-animation-dataset",
    "description": "Ubisoft La Forge - Animation Dataset",
    "stars": 0,
    "forks": 0,
    "languages": {
      "Python": 34253
    },
    "contributions_by_user": 0,
    "contribution_score": 16.73,
    "S_code": 33.45,
    "S_social": 0,
    "S_maint": 0
  },
  {
    "name": "wipeout",
    "full_name": "CedricGuillemet/wipeout",
    "html_url": "https://github.com/CedricGuillemet/wipeout",
    "description": "WipEout (PSX) Model Viewer in WebGL/Three.js",
    "stars": 0,
    "forks": 0,
    "languages": {
      "JavaScript": 59211,
      "HTML": 5828
    },
    "contributions_by_user": 0,
    "contribution_score": 31.76,
    "S_code": 63.51,
    "S_social": 0,
    "S_maint": 0
  },
  {
    "name": "bjsdemos",
    "full_name": "CedricGuillemet/bjsdemos",
    "html_url": "https://github.com/CedricGuillemet/bjsdemos",
    "description": "Repo for babylonjs demos",
    "stars": 0,
    "forks": 0,
    "languages": {},
    "contributions_by_user": 3,
    "contribution_score": 30.0,
    "S_code": 0.0,
    "S_social": 0,
    "S_maint": 3
  },
  {
    "name": "recastjs",
    "full_name": "CedricGuillemet/recastjs",
    "html_url": "https://github.com/CedricGuillemet/recastjs",
    "description": "Direct port of the Recast/Detour engine to JavaScript using Emscripten ",
    "stars": 0,
    "forks": 0,
    "languages": {
      "C++": 18286,
      "Python": 4318,
      "CMake": 2966
    },
    "contributions_by_user": 6,
    "contribution_score": 72.49,
    "S_code": 24.97,
    "S_social": 0,
    "S_maint": 6
  },
  {
    "name": "cgltf",
    "full_name": "CedricGuillemet/cgltf",
    "html_url": "https://github.com/CedricGuillemet/cgltf",
    "description": "Single-file C glTF loader",
    "stars": 0,
    "forks": 0,
    "languages": {
      "C": 118334,
      "C++": 23843,
      "Python": 2171,
      "CMake": 654
    },
    "contributions_by_user": 0,
    "contribution_score": 70.8,
    "S_code": 141.6,
    "S_social": 0,
    "S_maint": 0
  },
  {
    "name": "lib3mf",
    "full_name": "CedricGuillemet/lib3mf",
    "html_url": "https://github.com/CedricGuillemet/lib3mf",
    "description": "Lib3MF is the reference implementation of the 3D Manufacturing Format file standard",
    "stars": 0,
    "forks": 0,
    "languages": {
      "C++": 2333846,
      "C": 862032,
      "CMake": 49900,
      "Objective-C": 14804,
      "PowerShell": 6892,
      "Shell": 3632,
      "Batchfile": 703
    },
    "contributions_by_user": 0,
    "contribution_score": 1597.56,
    "S_code": 3195.13,
    "S_social": 0,
    "S_maint": 0
  },
  {
    "name": "patch-based-texture-synthesis",
    "full_name": "CedricGuillemet/patch-based-texture-synthesis",
    "html_url": "https://github.com/CedricGuillemet/patch-based-texture-synthesis",
    "description": "Based on \"Image Quilting for Texture Synthesis and Transfer\" and \"Real-Time Texture Synthesis by Patch-Based Sampling\" papers",
    "stars": 0,
    "forks": 0,
    "languages": {
      "Jupyter Notebook": 140328,
      "Python": 19146
    },
    "contributions_by_user": 0,
    "contribution_score": 77.87,
    "S_code": 155.74,
    "S_social": 0,
    "S_maint": 0
  },
  {
    "name": "recast.js",
    "full_name": "CedricGuillemet/recast.js",
    "html_url": "https://github.com/CedricGuillemet/recast.js",
    "description": "A wrapper for the RecastDetour navigation library for node and the browser",
    "stars": 0,
    "forks": 0,
    "languages": {
      "JavaScript": 6700207,
      "C": 549765,
      "C++": 221388,
      "Objective-C": 14815,
      "Makefile": 11749,
      "HTML": 9598,
      "CMake": 5915,
      "Roff": 4235
    },
    "contributions_by_user": 0,
    "contribution_score": 3670.74,
    "S_code": 7341.48,
    "S_social": 0,
    "S_maint": 0
  }
]