[
  {
    "name": "saimon24/devdactic-ionic_login",
    "stars": 87,
    "description": "Simple login example for ionic with AngularJS http://www.devdactic.com",
    "files": {
      "package.json": null,
      "go.mod": null,
      "pom.xml": null,
      "requirements.txt": null,
      "Cargo.toml": null,
      "Gemfile": null,
      "Dockerfile": null,
      "docker-compose.yml": null,
      ".github/workflows/ci.yml": null,
      "k8s.yaml": null,
      "helm/Chart.yaml": null
    }
  },
  {
    "name": "saimon24/ng-twitter",
    "stars": 53,
    "description": "AngularJS library for the Twitter REST Api",
    "files": {
      "package.json": "{\n    \"name\": \"ng-twitter-api\",\n    \"version\": \"0.1.5\",\n    \"description\": \"AngularJS Twitter REST Api wrapper library\",\n    \"author\": {\n        \"name\": \"Simon Reimler\",\n        \"url\": \"http://www.devdactic.com\"\n    },\n    \"homepage\": \"https://www.devdactic.com\",\n    \"devDependencies\": {\n        \"grunt\": \"~0.4.5\",\n        \"grunt-contrib-jshint\": \"~0.10.0\",\n        \"grunt-contrib-clean\": \"~0.6.0\",\n        \"grunt-contrib-uglify\": \"~0.5.0\",\n        \"grunt-contrib-concat\": \"^0.5.1\"\n    },\n    \"keywords\": [\n        \"angularjs\",\n        \"oauth\",\n        \"api\",\n        \"twitter\"\n    ],\n    \"license\": \"MIT\",\n    \"scripts\": {\n        \"test\": \"grunt test\"\n    }\n}\n",
      "go.mod": null,
      "pom.xml": null,
      "requirements.txt": null,
      "Cargo.toml": null,
      "Gemfile": null,
      "Dockerfile": null,
      "docker-compose.yml": null,
      ".github/workflows/ci.yml": null,
      "k8s.yaml": null,
      "helm/Chart.yaml": null
    }
  },
  {
    "name": "saimon24/react-native-resumable-upload-supabase",
    "stars": 42,
    "description": "无",
    "files": {
      "package.json": "{\n  \"scripts\": {\n    \"start\": \"expo start\",\n    \"android\": \"expo start --android\",\n    \"ios\": \"expo start --ios\",\n    \"web\": \"expo start --web\"\n  },\n  \"dependencies\": {\n    \"@react-native-async-storage/async-storage\": \"1.18.2\",\n    \"@supabase/supabase-js\": \"^2.26.0\",\n    \"@types/react\": \"~18.2.14\",\n    \"base64-arraybuffer\": \"^1.0.2\",\n    \"base64-js\": \"^1.5.1\",\n    \"expo\": \"^49.0.2\",\n    \"expo-constants\": \"~14.4.2\",\n    \"expo-file-system\": \"~15.4.2\",\n    \"expo-image-picker\": \"~14.3.1\",\n    \"expo-linking\": \"~5.0.2\",\n    \"expo-router\": \"2.0.0\",\n    \"expo-secure-store\": \"~12.3.1\",\n    \"expo-splash-screen\": \"~0.20.4\",\n    \"expo-status-bar\": \"~1.6.0\",\n    \"react\": \"18.2.0\",\n    \"react-dom\": \"18.2.0\",\n    \"react-native\": \"0.72.1\",\n    \"react-native-gesture-handler\": \"~2.12.0\",\n    \"react-native-loading-spinner-overlay\": \"^3.0.1\",\n    \"react-native-reanimated\": \"~3.3.0\",\n    \"react-native-safe-area-context\": \"4.6.3\",\n    \"react-native-screens\": \"~3.22.0\",\n    \"react-native-url-polyfill\": \"^1.3.0\",\n    \"react-native-web\": \"~0.19.6\",\n    \"typescript\": \"^5.1.3\"\n  },\n  \"devDependencies\": {\n    \"@babel/core\": \"^7.19.3\",\n    \"@babel/plugin-proposal-export-namespace-from\": \"^7.18.9\"\n  },\n  \"resolutions\": {\n    \"metro\": \"^0.73.7\",\n    \"metro-resolver\": \"^0.73.7\"\n  },\n  \"overrides\": {\n    \"metro\": \"^0.73.7\",\n    \"metro-resolver\": \"^0.73.7\"\n  },\n  \"name\": \"mycloudapp\",\n  \"version\": \"1.0.0\",\n  \"private\": true\n}\n",
      "go.mod": null,
      "pom.xml": null,
      "requirements.txt": null,
      "Cargo.toml": null,
      "Gemfile": null,
      "Dockerfile": null,
      "docker-compose.yml": null,
      ".github/workflows/ci.yml": null,
      "k8s.yaml": null,
      "helm/Chart.yaml": null
    }
  }
]