[
  {
    "name": "davidjgraph/sandbox",
    "stars": 0,
    "description": "无",
    "languages_breakdown": {},
    "files": {
      "README.md": "# sandbox\nUsing draw.io diagrams in github:\n\n![Test image](https://github.com/alderg/sandbox/raw/master/test.png)\n\n[Edit diagram](https://www.draw.io/?url=https%3A%2F%2Fraw.githubusercontent.com%2Falderg%2Fsandbox%2Fmaster%2Ftest.png)\n\nTo update the diagram, export as PNG+XML via File, Export as, PNG (with XML).\n"
    }
  },
  {
    "name": "davidjgraph/saveMacroTest",
    "stars": 0,
    "description": "无",
    "languages_breakdown": {
      "HTML": 2743,
      "JavaScript": 619
    },
    "files": {}
  },
  {
    "name": "davidjgraph/test",
    "stars": 0,
    "description": "无",
    "languages_breakdown": {},
    "files": {
      "README.md": "# test"
    }
  }
]