[
  {
    "name": "agilexrobotics/ugv_gazebo_sim",
    "stars": 271,
    "description": "gazebo_sim",
    "files": {
      "package.json": null,
      "go.mod": null,
      "pom.xml": null,
      "requirements.txt": null,
      "Cargo.toml": null,
      "Gemfile": null,
      "Dockerfile": null,
      "docker-compose.yml": null,
      ".github/workflows/ci.yml": null,
      "k8s.yaml": null,
      "helm/Chart.yaml": null
    }
  },
  {
    "name": "agilexrobotics/piper_sdk",
    "stars": 230,
    "description": "The code for controlling the Piper robotic arm",
    "files": {
      "package.json": null,
      "go.mod": null,
      "pom.xml": null,
      "requirements.txt": null,
      "Cargo.toml": null,
      "Gemfile": null,
      "Dockerfile": null,
      "docker-compose.yml": null,
      ".github/workflows/ci.yml": null,
      "k8s.yaml": null,
      "helm/Chart.yaml": null
    }
  },
  {
    "name": "agilexrobotics/piper_ros",
    "stars": 222,
    "description": "piper ros workspace",
    "files": {
      "package.json": null,
      "go.mod": null,
      "pom.xml": null,
      "requirements.txt": null,
      "Cargo.toml": null,
      "Gemfile": null,
      "Dockerfile": null,
      "docker-compose.yml": null,
      ".github/workflows/ci.yml": null,
      "k8s.yaml": null,
      "helm/Chart.yaml": null
    }
  }
]